Workbook

Sheet consolidado_notas
G1: 0.1 | H1: 0.15 | I1: 0.1 | J1: 0.15 | K1: 0.1 | L1: 0.15 | M1: 0.1 | N1: 0.15 | O1: Notas a subir
A2: Nombre | B2: Correo | C2: grupo caso HR | D2: Grupo caso marketing | E2: grupo Salud | F2: Grupo caso Finanzas | G2: Seguimietno HR | H2: TRabajo HR | I2: seguimiento Marketing | J2: Trabajo Marketing | K2: seguimiento Salud | L2: Trabajo Salud | M2: seguimiento Finanzas | N2: Trabajo finanzas | O2: HR | P2: Marketing | Q2: Salud | R2: Finanzas | S2: Asistencia | T2: Bonificaciones | U2: En amarillo notas con las bonificaciones
A3: ALVAREZ FERNANDEZ ALANIS | B3: alanis.alvarez@udea.edu.co | C3: 1 | D3: 1 | E3: 1 | F3: 1 | G3: =IFERROR(VLOOKUP(B3,seguimiento_HR!B:J,2,0),"") -> 4.6 | H3: =IFERROR(VLOOKUP(C3&$H$2&"Total",retroalimenación!D:F,3,0),"") -> 5 | I3: =IFERROR(VLOOKUP(B3,seguimiento_mark!B:C,2,0),"") -> 3 | J3: =IFERROR(VLOOKUP(D3&$J$2&"Total",retroalimenación!D:F,3,0),"") -> 5 | K3: =IFERROR(VLOOKUP(B3,seguimiento_salud!B:C,2,0),"") -> 4.9 | L3: =IFERROR(VLOOKUP(E3&$L$2&"Total",retroalimenación!D:F,3,0),"") -> 5 | M3: =IFERROR(VLOOKUP(B3,seguimiento_finanzas!B:C,2,0),"") -> 4.9 | N3: =IFERROR(VLOOKUP(E3&$N$2&"Total",retroalimenación!D:F,3,0),"") -> 5 | O3: =ROUND(SUMPRODUCT(G3:H3,$G$1:$H$1)*4,1) -> 4.8 | P3: =ROUND(SUMPRODUCT(I3:J3,$I$1:$J$1)*4,1)+0.4 -> 4.6 | Q3: =ROUND(SUMPRODUCT(K3:L3,$K$1:$L$1)*4,1) -> 5 | R3: =ROUND(SUMPRODUCT(M3:N3,$M$1:$N$1)*4,1) -> 5 | T3: =VLOOKUP(B3,bonificaciones!B:C,2,0) -> 0.4
A4: ÁLVAREZ LÓPEZ ALEJANDRO | B4: alejandro.alvarezl@udea.edu.co | C4: 5 | D4: 5 | E4: 5 | F4: 5 | G4: 4.7 | H4: =IFERROR(VLOOKUP(C4&$H$2&"Total",retroalimenación!D:F,3,0),"") -> 5 | I4: 4.7 | J4: =IFERROR(VLOOKUP(D4&$J$2&"Total",retroalimenación!D:F,3,0),"") -> 4.275 | K4: 4.7 | L4: =IFERROR(VLOOKUP(E4&$L$2&"Total",retroalimenación!D:F,3,0),"") -> 5 | M4: 4.7 | N4: =IFERROR(VLOOKUP(E4&$N$2&"Total",retroalimenación!D:F,3,0),"") -> 5 | O4: =ROUND(SUMPRODUCT(G4:H4,$G$1:$H$1)*4,1) -> 4.9 | P4: =ROUND(SUMPRODUCT(I4:J4,$I$1:$J$1)*4,1) -> 4.4 | Q4: =ROUND(SUMPRODUCT(K4:L4,$K$1:$L$1)*4,1) -> 4.9 | R4: =ROUND(SUMPRODUCT(M4:N4,$M$1:$N$1)*4,1) -> 4.9 | S4: Sí | T4: =VLOOKUP(B4,bonificaciones!B:C,2,0) -> 0
A5: AMAYA LEÓN ALEXÁNDER | B5: alexander.amaya@udea.edu.co | C5: 2 | D5: 2 | E5: 2 | F5: 2 | G5: =IFERROR(VLOOKUP(B5,seguimiento_HR!B:J,2,0),"") -> 4.1 | H5: =IFERROR(VLOOKUP(C5&$H$2&"Total",retroalimenación!D:F,3,0),"") -> 5 | I5: =IFERROR(VLOOKUP(B5,seguimiento_mark!B:C,2,0),"") -> 2 | J5: =IFERROR(VLOOKUP(D5&$J$2&"Total",retroalimenación!D:F,3,0),"") -> 5 | K5: =IFERROR(VLOOKUP(B5,seguimiento_salud!B:C,2,0),"") -> 4 | L5: =IFERROR(VLOOKUP(E5&$L$2&"Total",retroalimenación!D:F,3,0),"") -> 5 | M5: =IFERROR(VLOOKUP(B5,seguimiento_finanzas!B:C,2,0),"") -> 4.9 | N5: =IFERROR(VLOOKUP(E5&$N$2&"Total",retroalimenación!D:F,3,0),"") -> 4.69 | O5: =ROUND(SUMPRODUCT(G5:H5,$G$1:$H$1)*4,1) -> 4.6 | P5: =ROUND(SUMPRODUCT(I5:J5,$I$1:$J$1)*4,1)+0.4 -> 4.2 | Q5: =ROUND(SUMPRODUCT(K5:L5,$K$1:$L$1)*4,1) -> 4.6 | R5: =ROUND(SUMPRODUCT(M5:N5,$M$1:$N$1)*4,1) -> 4.8 | T5: =VLOOKUP(B5,bonificaciones!B:C,2,0) -> 0.6
A6: ARABIA ÁLVAREZ PAOLA ANDREA | B6: paola.arabia@udea.edu.co | C6: 8 | D6: 8 | E6: 8 | F6: 8 | G6: 4.5 | H6: =IFERROR(VLOOKUP(C6&$H$2&"Total",retroalimenación!D:F,3,0),"") -> 3.775 | I6: 4.5 | J6: =IFERROR(VLOOKUP(D6&$J$2&"Total",retroalimenación!D:F,3,0),"") -> 2.825 | K6: 4.5 | L6: =IFERROR(VLOOKUP(E6&$L$2&"Total",retroalimenación!D:F,3,0),"") -> 4.175 | M6: 4.5 | N6: =IFERROR(VLOOKUP(E6&$N$2&"Total",retroalimenación!D:F,3,0),"") -> 5 | O6: =ROUND(SUMPRODUCT(G6:H6,$G$1:$H$1)*4,1) -> 4.1 | P6: =ROUND(SUMPRODUCT(I6:J6,$I$1:$J$1)*4,1) -> 3.5 | Q6: =ROUND(SUMPRODUCT(K6:L6,$K$1:$L$1)*4,1) -> 4.3 | R6: =ROUND(SUMPRODUCT(M6:N6,$M$1:$N$1)*4,1) -> 4.8 | S6: Sí | T6: =VLOOKUP(B6,bonificaciones!B:C,2,0) -> 0
A7: ARROYAVE MURILLO JUAN DIEGO | B7: juan.arroyave14@udea.edu.co | C7: 5 | D7: 5 | E7: 5 | F7: 5 | G7: 4.8 | H7: =IFERROR(VLOOKUP(C7&$H$2&"Total",retroalimenación!D:F,3,0),"") -> 5 | I7: 4.8 | J7: =IFERROR(VLOOKUP(D7&$J$2&"Total",retroalimenación!D:F,3,0),"") -> 4.275 | K7: 4.8 | L7: =IFERROR(VLOOKUP(E7&$L$2&"Total",retroalimenación!D:F,3,0),"") -> 5 | M7: 4.8 | N7: =IFERROR(VLOOKUP(E7&$N$2&"Total",retroalimenación!D:F,3,0),"") -> 5 | O7: =ROUND(SUMPRODUCT(G7:H7,$G$1:$H$1)*4,1) -> 4.9 | P7: =ROUND(SUMPRODUCT(I7:J7,$I$1:$J$1)*4,1) -> 4.5 | Q7: =ROUND(SUMPRODUCT(K7:L7,$K$1:$L$1)*4,1) -> 4.9 | R7: =ROUND(SUMPRODUCT(M7:N7,$M$1:$N$1)*4,1) -> 4.9 | S7: Sí | T7: =VLOOKUP(B7,bonificaciones!B:C,2,0) -> 0
A8: BETANCOURT FUENTES LAURA CAMILA | B8: laura.betancourt1@udea.edu.co | C8: 3 | D8: 3 | E8: 3 | F8: 3 | G8: =IFERROR(VLOOKUP(B8,seguimiento_HR!B:J,2,0),"") -> 4.4 | H8: =IFERROR(VLOOKUP(C8&$H$2&"Total",retroalimenación!D:F,3,0),"") -> 4.485 | I8: =IFERROR(VLOOKUP(B8,seguimiento_mark!B:C,2,0),"") -> 4.8 | J8: =IFERROR(VLOOKUP(D8&$J$2&"Total",retroalimenación!D:F,3,0),"") -> 4.485 | K8: =IFERROR(VLOOKUP(B8,seguimiento_salud!B:C,2,0),"") -> 3.7 | L8: =IFERROR(VLOOKUP(E8&$L$2&"Total",retroalimenación!D:F,3,0),"") -> 5 | M8: =IFERROR(VLOOKUP(B8,seguimiento_finanzas!B:C,2,0),"") -> 4.3 | N8: =IFERROR(VLOOKUP(E8&$N$2&"Total",retroalimenación!D:F,3,0),"") -> 3.5 | O8: =ROUND(SUMPRODUCT(G8:H8,$G$1:$H$1)*4,1) -> 4.5 | P8: =ROUND(SUMPRODUCT(I8:J8,$I$1:$J$1)*4,1) -> 4.6 | Q8: =ROUND(SUMPRODUCT(K8:L8,$K$1:$L$1)*4,1) -> 4.5 | R8: =ROUND(SUMPRODUCT(M8:N8,$M$1:$N$1)*4,1)+0.4 -> 4.2 | T8: =VLOOKUP(B8,bonificaciones!B:C,2,0) -> 0.4
A9: BLANDÓN RAMÍREZ MANUELA | B9: manuela.blandon@udea.edu.co | C9: 2 | D9: 2 | E9: 2 | F9: 2 | G9: =IFERROR(VLOOKUP(B9,seguimiento_HR!B:J,2,0),"") -> 4.6 | H9: =IFERROR(VLOOKUP(C9&$H$2&"Total",retroalimenación!D:F,3,0),"") -> 5 | I9: =IFERROR(VLOOKUP(B9,seguimiento_mark!B:C,2,0),"") -> 5 | J9: =IFERROR(VLOOKUP(D9&$J$2&"Total",retroalimenación!D:F,3,0),"") -> 5 | K9: =IFERROR(VLOOKUP(B9,seguimiento_salud!B:C,2,0),"") -> 5 | L9: =IFERROR(VLOOKUP(E9&$L$2&"Total",retroalimenación!D:F,3,0),"") -> 5 | M9: =IFERROR(VLOOKUP(B9,seguimiento_finanzas!B:C,2,0),"") -> 5 | N9: =IFERROR(VLOOKUP(E9&$N$2&"Total",retroalimenación!D:F,3,0),"") -> 4.69 | O9: =ROUND(SUMPRODUCT(G9:H9,$G$1:$H$1)*4,1)+0.2 -> 5 | P9: =ROUND(SUMPRODUCT(I9:J9,$I$1:$J$1)*4,1) -> 5 | Q9: =ROUND(SUMPRODUCT(K9:L9,$K$1:$L$1)*4,1) -> 5 | R9: =ROUND(SUMPRODUCT(M9:N9,$M$1:$N$1)*4,1)+0.2 -> 5 | T9: =VLOOKUP(B9,bonificaciones!B:C,2,0) -> 0.6
A10: CAICEDO AGUIRRE MATEO | B10: mateo.caicedo@udea.edu.co | C10: 7 | D10: 8 | E10: 8 | F10: 8 | G10: =IFERROR(VLOOKUP(B10,seguimiento_HR!B:J,2,0),"") -> 4.5 | H10: =IFERROR(VLOOKUP(C10&$H$2&"Total",retroalimenación!D:F,3,0),"") -> 3.9 | I10: =IFERROR(VLOOKUP(B10,seguimiento_mark!B:C,2,0),"") -> 2.6 | J10: =IFERROR(VLOOKUP(D10&$J$2&"Total",retroalimenación!D:F,3,0),"") -> 2.825 | K10: =IFERROR(VLOOKUP(B10,seguimiento_salud!B:C,2,0),"") -> 3.8 | L10: =IFERROR(VLOOKUP(E10&$L$2&"Total",retroalimenación!D:F,3,0),"") -> 4.175 | M10: =IFERROR(VLOOKUP(B10,seguimiento_finanzas!B:C,2,0),"") -> 0 | N10: =IFERROR(VLOOKUP(E10&$N$2&"Total",retroalimenación!D:F,3,0),"") -> 5 | O10: =ROUND(SUMPRODUCT(G10:H10,$G$1:$H$1)*4,1) -> 4.1 | P10: =ROUND(SUMPRODUCT(I10:J10,$I$1:$J$1)*4,1) -> 2.7 | Q10: =ROUND(SUMPRODUCT(K10:L10,$K$1:$L$1)*4,1) -> 4 | R10: =ROUND(SUMPRODUCT(M10:N10,$M$1:$N$1)*4,1) -> 3 | T10: =VLOOKUP(B10,bonificaciones!B:C,2,0) -> 0
A11: CARDONA MOLINA JUAN ESTEBAN | B11: esteban.cardona6@udea.edu.co | C11: 1 | D11: 1 | E11: 1 | F11: 1 | G11: =IFERROR(VLOOKUP(B11,seguimiento_HR!B:J,2,0),"") -> 4.8 | H11: =IFERROR(VLOOKUP(C11&$H$2&"Total",retroalimenación!D:F,3,0),"") -> 5 | I11: =IFERROR(VLOOKUP(B11,seguimiento_mark!B:C,2,0),"") -> 5 | J11: =IFERROR(VLOOKUP(D11&$J$2&"Total",retroalimenación!D:F,3,0),"") -> 5 | K11: =IFERROR(VLOOKUP(B11,seguimiento_salud!B:C,2,0),"") -> 4.9 | L11: =IFERROR(VLOOKUP(E11&$L$2&"Total",retroalimenación!D:F,3,0),"") -> 5 | M11: =IFERROR(VLOOKUP(B11,seguimiento_finanzas!B:C,2,0),"") -> 4.9 | N11: =IFERROR(VLOOKUP(E11&$N$2&"Total",retroalimenación!D:F,3,0),"") -> 5 | O11: =ROUND(SUMPRODUCT(G11:H11,$G$1:$H$1)*4,1)+0.1 -> 5 | P11: =ROUND(SUMPRODUCT(I11:J11,$I$1:$J$1)*4,1) -> 5 | Q11: =ROUND(SUMPRODUCT(K11:L11,$K$1:$L$1)*4,1) -> 5 | R11: =ROUND(SUMPRODUCT(M11:N11,$M$1:$N$1)*4,1) -> 5 | T11: =VLOOKUP(B11,bonificaciones!B:C,2,0) -> 0.2
A12: CONTRERAS TRILLOS OSIRIS | B12: osiris.contreras@udea.edu.co | C12: 4 | D12: 4 | E12: 4 | F12: 4 | G12: 4.5 | H12: =IFERROR(VLOOKUP(C12&$H$2&"Total",retroalimenación!D:F,3,0),"") -> 4.605 | I12: =IFERROR(VLOOKUP(B12,seguimiento_mark!B:C,2,0),"") -> 4.6 | J12: =IFERROR(VLOOKUP(D12&$J$2&"Total",retroalimenación!D:F,3,0),"") -> 5 | K12: 4.5 | L12: =IFERROR(VLOOKUP(E12&$L$2&"Total",retroalimenación!D:F,3,0),"") -> 5 | M12: 4.5 | N12: =IFERROR(VLOOKUP(E12&$N$2&"Total",retroalimenación!D:F,3,0),"") -> 4.65 | O12: =ROUND(SUMPRODUCT(G12:H12,$G$1:$H$1)*4,1) -> 4.6 | P12: =ROUND(SUMPRODUCT(I12:J12,$I$1:$J$1)*4,1) -> 4.8 | Q12: =ROUND(SUMPRODUCT(K12:L12,$K$1:$L$1)*4,1) -> 4.8 | R12: =ROUND(SUMPRODUCT(M12:N12,$M$1:$N$1)*4,1)+0.2 -> 4.8 | S12: Sí | T12: =VLOOKUP(B12,bonificaciones!B:C,2,0) -> 0.2
A13: CUARTAS GIL SEBASTIAN | B13: sebastian.cuartas1@udea.edu.co | C13: 7 | D13: 7 | E13: 7 | F13: 7 | G13: =IFERROR(VLOOKUP(B13,seguimiento_HR!B:J,2,0),"") -> 4.5 | H13: =IFERROR(VLOOKUP(C13&$H$2&"Total",retroalimenación!D:F,3,0),"") -> 3.9 | I13: =IFERROR(VLOOKUP(B13,seguimiento_mark!B:C,2,0),"") -> 3.8 | J13: =IFERROR(VLOOKUP(D13&$J$2&"Total",retroalimenación!D:F,3,0),"") -> 4.22 | K13: =IFERROR(VLOOKUP(B13,seguimiento_salud!B:C,2,0),"") -> 2.8 | L13: =IFERROR(VLOOKUP(E13&$L$2&"Total",retroalimenación!D:F,3,0),"") -> 4.325 | M13: =IFERROR(VLOOKUP(B13,seguimiento_finanzas!B:C,2,0),"") -> 4.4 | N13: =IFERROR(VLOOKUP(E13&$N$2&"Total",retroalimenación!D:F,3,0),"") -> 3.25 | O13: =ROUND(SUMPRODUCT(G13:H13,$G$1:$H$1)*4,1) -> 4.1 | P13: =ROUND(SUMPRODUCT(I13:J13,$I$1:$J$1)*4,1) -> 4.1 | Q13: =ROUND(SUMPRODUCT(K13:L13,$K$1:$L$1)*4,1) -> 3.7 | R13: =ROUND(SUMPRODUCT(M13:N13,$M$1:$N$1)*4,1) -> 3.7 | T13: =VLOOKUP(B13,bonificaciones!B:C,2,0) -> 0
A14: DEL VALLE CORREA DAYANA SOFIA | B14: dayana.delvalle@udea.edu.co | C14: 2 | D14: 2 | E14: 2 | F14: 2 | G14: =IFERROR(VLOOKUP(B14,seguimiento_HR!B:J,2,0),"") -> 4.7 | H14: =IFERROR(VLOOKUP(C14&$H$2&"Total",retroalimenación!D:F,3,0),"") -> 5 | I14: =IFERROR(VLOOKUP(B14,seguimiento_mark!B:C,2,0),"") -> 4 | J14: =IFERROR(VLOOKUP(D14&$J$2&"Total",retroalimenación!D:F,3,0),"") -> 5 | K14: =IFERROR(VLOOKUP(B14,seguimiento_salud!B:C,2,0),"") -> 4 | L14: =IFERROR(VLOOKUP(E14&$L$2&"Total",retroalimenación!D:F,3,0),"") -> 5 | M14: =IFERROR(VLOOKUP(B14,seguimiento_finanzas!B:C,2,0),"") -> 4.8 | N14: =IFERROR(VLOOKUP(E14&$N$2&"Total",retroalimenación!D:F,3,0),"") -> 4.69 | O14: =ROUND(SUMPRODUCT(G14:H14,$G$1:$H$1)*4,1) -> 4.9 | P14: =ROUND(SUMPRODUCT(I14:J14,$I$1:$J$1)*4,1) -> 4.6 | Q14: =ROUND(SUMPRODUCT(K14:L14,$K$1:$L$1)*4,1) -> 4.6 | R14: =ROUND(SUMPRODUCT(M14:N14,$M$1:$N$1)*4,1) -> 4.7 | T14: =VLOOKUP(B14,bonificaciones!B:C,2,0) -> 0
A15: DUSSAN PUERTA ESTEFANIA | B15: estefania.dussan@udea.edu.co | C15: 5 | D15: 5 | E15: 5 | F15: 5 | G15: =IFERROR(VLOOKUP(B15,seguimiento_HR!B:J,2,0),"") -> 4.8 | H15: =IFERROR(VLOOKUP(C15&$H$2&"Total",retroalimenación!D:F,3,0),"") -> 5 | I15: =IFERROR(VLOOKUP(B15,seguimiento_mark!B:C,2,0),"") -> 3 | J15: =IFERROR(VLOOKUP(D15&$J$2&"Total",retroalimenación!D:F,3,0),"") -> 4.275 | K15: =IFERROR(VLOOKUP(B15,seguimiento_salud!B:C,2,0),"") -> 4.8 | L15: =IFERROR(VLOOKUP(E15&$L$2&"Total",retroalimenación!D:F,3,0),"") -> 5 | M15: =IFERROR(VLOOKUP(B15,seguimiento_finanzas!B:C,2,0),"") -> 3.8 | N15: =IFERROR(VLOOKUP(E15&$N$2&"Total",retroalimenación!D:F,3,0),"") -> 5 | O15: =ROUND(SUMPRODUCT(G15:H15,$G$1:$H$1)*4,1) -> 4.9 | P15: =ROUND(SUMPRODUCT(I15:J15,$I$1:$J$1)*4,1) -> 3.8 | Q15: =ROUND(SUMPRODUCT(K15:L15,$K$1:$L$1)*4,1) -> 4.9 | R15: =ROUND(SUMPRODUCT(M15:N15,$M$1:$N$1)*4,1) -> 4.5 | S15: Sí | T15: =VLOOKUP(B15,bonificaciones!B:C,2,0) -> 0
A16: GIL PACHECO GILBERTO JOSÉ | B16: gilberto.gil1@udea.edu.co | C16: 3 | D16: 3 | E16: 3 | F16: 3 | G16: =IFERROR(VLOOKUP(B16,seguimiento_HR!B:J,2,0),"") -> 4.5 | H16: =IFERROR(VLOOKUP(C16&$H$2&"Total",retroalimenación!D:F,3,0),"") -> 4.485 | I16: =IFERROR(VLOOKUP(B16,seguimiento_mark!B:C,2,0),"") -> 3.8 | J16: =IFERROR(VLOOKUP(D16&$J$2&"Total",retroalimenación!D:F,3,0),"") -> 4.485 | K16: =IFERROR(VLOOKUP(B16,seguimiento_salud!B:C,2,0),"") -> 3.7 | L16: =IFERROR(VLOOKUP(E16&$L$2&"Total",retroalimenación!D:F,3,0),"") -> 5 | M16: =IFERROR(VLOOKUP(B16,seguimiento_finanzas!B:C,2,0),"") -> 1.9 | N16: =IFERROR(VLOOKUP(E16&$N$2&"Total",retroalimenación!D:F,3,0),"") -> 3.5 | O16: =ROUND(SUMPRODUCT(G16:H16,$G$1:$H$1)*4,1) -> 4.5 | P16: =ROUND(SUMPRODUCT(I16:J16,$I$1:$J$1)*4,1) -> 4.2 | Q16: =ROUND(SUMPRODUCT(K16:L16,$K$1:$L$1)*4,1) -> 4.5 | R16: =ROUND(SUMPRODUCT(M16:N16,$M$1:$N$1)*4,1) -> 2.9 | T16: =VLOOKUP(B16,bonificaciones!B:C,2,0) -> 0
A17: GUERRERO LOBO LEIDYS | B17: leidys.guerrero@udea.edu.co | C17: 8 | D17: 8 | E17: 8 | F17: 8 | G17: 4.4 | H17: =IFERROR(VLOOKUP(C17&$H$2&"Total",retroalimenación!D:F,3,0),"") -> 3.775 | I17: 4.4 | J17: =IFERROR(VLOOKUP(D17&$J$2&"Total",retroalimenación!D:F,3,0),"") -> 2.825 | K17: 4.4 | L17: =IFERROR(VLOOKUP(E17&$L$2&"Total",retroalimenación!D:F,3,0),"") -> 4.175 | M17: 4.4 | N17: =IFERROR(VLOOKUP(E17&$N$2&"Total",retroalimenación!D:F,3,0),"") -> 5 | O17: =ROUND(SUMPRODUCT(G17:H17,$G$1:$H$1)*4,1) -> 4 | P17: =ROUND(SUMPRODUCT(I17:J17,$I$1:$J$1)*4,1) -> 3.5 | Q17: =ROUND(SUMPRODUCT(K17:L17,$K$1:$L$1)*4,1) -> 4.3 | R17: =ROUND(SUMPRODUCT(M17:N17,$M$1:$N$1)*4,1) -> 4.8 | S17: Sí | T17: =VLOOKUP(B17,bonificaciones!B:C,2,0) -> 0
A18: GUZMAN ZORRILLA NATALIA XIMENA | B18: natalia.guzmanz@udea.edu.co | C18: 7 | D18: 7 | E18: 7 | F18: 7 | G18: =IFERROR(VLOOKUP(B18,seguimiento_HR!B:J,2,0),"") -> 4.3 | H18: =IFERROR(VLOOKUP(C18&$H$2&"Total",retroalimenación!D:F,3,0),"") -> 3.9 | I18: =IFERROR(VLOOKUP(B18,seguimiento_mark!B:C,2,0),"") -> 3.8 | J18: =IFERROR(VLOOKUP(D18&$J$2&"Total",retroalimenación!D:F,3,0),"") -> 4.22 | K18: =IFERROR(VLOOKUP(B18,seguimiento_salud!B:C,2,0),"") -> 4.8 | L18: =IFERROR(VLOOKUP(E18&$L$2&"Total",retroalimenación!D:F,3,0),"") -> 4.325 | M18: =IFERROR(VLOOKUP(B18,seguimiento_finanzas!B:C,2,0),"") -> 4.5 | N18: =IFERROR(VLOOKUP(E18&$N$2&"Total",retroalimenación!D:F,3,0),"") -> 3.25 | O18: =ROUND(SUMPRODUCT(G18:H18,$G$1:$H$1)*4,1) -> 4.1 | P18: =ROUND(SUMPRODUCT(I18:J18,$I$1:$J$1)*4,1) -> 4.1 | Q18: =ROUND(SUMPRODUCT(K18:L18,$K$1:$L$1)*4,1) -> 4.5 | R18: =ROUND(SUMPRODUCT(M18:N18,$M$1:$N$1)*4,1)+0.4 -> 4.2 | T18: =VLOOKUP(B18,bonificaciones!B:C,2,0) -> 0.4
A19: MARIN ZULUAGA SIMON | B19: simon.marinz@udea.edu.co | C19: 6 | D19: 7 | E19: 7 | F19: 7 | G19: =IFERROR(VLOOKUP(B19,seguimiento_HR!B:J,2,0),"") -> 4.3 | H19: =IFERROR(VLOOKUP(C19&$H$2&"Total",retroalimenación!D:F,3,0),"") -> 4.33 | I19: =IFERROR(VLOOKUP(B19,seguimiento_mark!B:C,2,0),"") -> 3.8 | J19: =IFERROR(VLOOKUP(D19&$J$2&"Total",retroalimenación!D:F,3,0),"") -> 4.22 | K19: =IFERROR(VLOOKUP(B19,seguimiento_salud!B:C,2,0),"") -> 3.8 | L19: =IFERROR(VLOOKUP(E19&$L$2&"Total",retroalimenación!D:F,3,0),"") -> 4.325 | M19: =IFERROR(VLOOKUP(B19,seguimiento_finanzas!B:C,2,0),"") -> 3.3 | N19: =IFERROR(VLOOKUP(E19&$N$2&"Total",retroalimenación!D:F,3,0),"") -> 3.25 | O19: =ROUND(SUMPRODUCT(G19:H19,$G$1:$H$1)*4,1) -> 4.3 | P19: =ROUND(SUMPRODUCT(I19:J19,$I$1:$J$1)*4,1) -> 4.1 | Q19: =ROUND(SUMPRODUCT(K19:L19,$K$1:$L$1)*4,1) -> 4.1 | R19: =ROUND(SUMPRODUCT(M19:N19,$M$1:$N$1)*4,1) -> 3.3 | T19: =VLOOKUP(B19,bonificaciones!B:C,2,0) -> 0
A20: MOLINA AMAYA AURA MARÍA | B20: aura.molina@udea.edu.co | C20: 3 | D20: 3 | E20: 3 | F20: 3 | G20: =IFERROR(VLOOKUP(B20,seguimiento_HR!B:J,2,0),"") -> 3 | H20: =IFERROR(VLOOKUP(C20&$H$2&"Total",retroalimenación!D:F,3,0),"") -> 4.485 | I20: =IFERROR(VLOOKUP(B20,seguimiento_mark!B:C,2,0),"") -> 2.8 | J20: =IFERROR(VLOOKUP(D20&$J$2&"Total",retroalimenación!D:F,3,0),"") -> 4.485 | K20: =IFERROR(VLOOKUP(B20,seguimiento_salud!B:C,2,0),"") -> 4.7 | L20: =IFERROR(VLOOKUP(E20&$L$2&"Total",retroalimenación!D:F,3,0),"") -> 5 | M20: =IFERROR(VLOOKUP(B20,seguimiento_finanzas!B:C,2,0),"") -> 1.9 | N20: =IFERROR(VLOOKUP(E20&$N$2&"Total",retroalimenación!D:F,3,0),"") -> 3.5 | O20: =ROUND(SUMPRODUCT(G20:H20,$G$1:$H$1)*4,1) -> 3.9 | P20: =ROUND(SUMPRODUCT(I20:J20,$I$1:$J$1)*4,1) -> 3.8 | Q20: =ROUND(SUMPRODUCT(K20:L20,$K$1:$L$1)*4,1) -> 4.9 | R20: =ROUND(SUMPRODUCT(M20:N20,$M$1:$N$1)*4,1) -> 2.9 | T20: =VLOOKUP(B20,bonificaciones!B:C,2,0) -> 0
A21: MOLINA OCAMPO JUAN JOSE | B21: juanj.molina1@udea.edu.co | C21: 4 | D21: 4 | E21: 4 | F21: 4 | G21: =IFERROR(VLOOKUP(B21,seguimiento_HR!B:J,2,0),"") -> 4.4 | H21: =IFERROR(VLOOKUP(C21&$H$2&"Total",retroalimenación!D:F,3,0),"") -> 4.605 | I21: =IFERROR(VLOOKUP(B21,seguimiento_mark!B:C,2,0),"") -> 3.9 | J21: =IFERROR(VLOOKUP(D21&$J$2&"Total",retroalimenación!D:F,3,0),"") -> 5 | K21: =IFERROR(VLOOKUP(B21,seguimiento_salud!B:C,2,0),"") -> 4.8 | L21: =IFERROR(VLOOKUP(E21&$L$2&"Total",retroalimenación!D:F,3,0),"") -> 5 | M21: =IFERROR(VLOOKUP(B21,seguimiento_finanzas!B:C,2,0),"") -> 2.4 | N21: =IFERROR(VLOOKUP(E21&$N$2&"Total",retroalimenación!D:F,3,0),"") -> 4.65 | O21: =ROUND(SUMPRODUCT(G21:H21,$G$1:$H$1)*4,1) -> 4.5 | P21: =ROUND(SUMPRODUCT(I21:J21,$I$1:$J$1)*4,1) -> 4.6 | Q21: =ROUND(SUMPRODUCT(K21:L21,$K$1:$L$1)*4,1) -> 4.9 | R21: =ROUND(SUMPRODUCT(M21:N21,$M$1:$N$1)*4,1) -> 3.8 | T21: =VLOOKUP(B21,bonificaciones!B:C,2,0) -> 0
A22: OSORIO LÓPEZ JUAN FELIPE | B22: jfelipe.osorio@udea.edu.co | C22: 4 | D22: 4 | E22: 4 | F22: 4 | G22: 5 | H22: =IFERROR(VLOOKUP(C22&$H$2&"Total",retroalimenación!D:F,3,0),"") -> 4.605 | I22: 5 | J22: =IFERROR(VLOOKUP(D22&$J$2&"Total",retroalimenación!D:F,3,0),"") -> 5 | K22: 5 | L22: =IFERROR(VLOOKUP(E22&$L$2&"Total",retroalimenación!D:F,3,0),"") -> 5 | M22: 5 | N22: =IFERROR(VLOOKUP(E22&$N$2&"Total",retroalimenación!D:F,3,0),"") -> 4.65 | O22: =ROUND(SUMPRODUCT(G22:H22,$G$1:$H$1)*4,1)+0.2 -> 5 | P22: =ROUND(SUMPRODUCT(I22:J22,$I$1:$J$1)*4,1) -> 5 | Q22: =ROUND(SUMPRODUCT(K22:L22,$K$1:$L$1)*4,1) -> 5 | R22: =ROUND(SUMPRODUCT(M22:N22,$M$1:$N$1)*4,1)+0.2 -> 5 | S22: Sí | T22: =VLOOKUP(B22,bonificaciones!B:C,2,0) -> 1
A23: PEREZ CASTILLA KAREN MARCELA | B23: karen.perezc@udea.edu.co | C23: 2 | D23: 2 | E23: 2 | F23: 2 | G23: =IFERROR(VLOOKUP(B23,seguimiento_HR!B:J,2,0),"") -> 4.7 | H23: =IFERROR(VLOOKUP(C23&$H$2&"Total",retroalimenación!D:F,3,0),"") -> 5 | I23: =IFERROR(VLOOKUP(B23,seguimiento_mark!B:C,2,0),"") -> 5 | J23: =IFERROR(VLOOKUP(D23&$J$2&"Total",retroalimenación!D:F,3,0),"") -> 5 | K23: =IFERROR(VLOOKUP(B23,seguimiento_salud!B:C,2,0),"") -> 5 | L23: =IFERROR(VLOOKUP(E23&$L$2&"Total",retroalimenación!D:F,3,0),"") -> 5 | M23: =IFERROR(VLOOKUP(B23,seguimiento_finanzas!B:C,2,0),"") -> 5 | N23: =IFERROR(VLOOKUP(E23&$N$2&"Total",retroalimenación!D:F,3,0),"") -> 4.69 | O23: =ROUND(SUMPRODUCT(G23:H23,$G$1:$H$1)*4,1)+0.1 -> 5 | P23: =ROUND(SUMPRODUCT(I23:J23,$I$1:$J$1)*4,1) -> 5 | Q23: =ROUND(SUMPRODUCT(K23:L23,$K$1:$L$1)*4,1) -> 5 | R23: =ROUND(SUMPRODUCT(M23:N23,$M$1:$N$1)*4,1)+0.2 -> 5 | T23: =VLOOKUP(B23,bonificaciones!B:C,2,0) -> 0.4
A24: RESTREPO OLARTE SANTIAGO | B24: santiago.restrepo23@udea.edu.co | C24: 1 | D24: 1 | E24: 1 | F24: 1 | G24: =IFERROR(VLOOKUP(B24,seguimiento_HR!B:J,2,0),"") -> 4.6 | H24: =IFERROR(VLOOKUP(C24&$H$2&"Total",retroalimenación!D:F,3,0),"") -> 5 | I24: =IFERROR(VLOOKUP(B24,seguimiento_mark!B:C,2,0),"") -> 4 | J24: =IFERROR(VLOOKUP(D24&$J$2&"Total",retroalimenación!D:F,3,0),"") -> 5 | K24: =IFERROR(VLOOKUP(B24,seguimiento_salud!B:C,2,0),"") -> 4.9 | L24: =IFERROR(VLOOKUP(E24&$L$2&"Total",retroalimenación!D:F,3,0),"") -> 5 | M24: =IFERROR(VLOOKUP(B24,seguimiento_finanzas!B:C,2,0),"") -> 4.9 | N24: =IFERROR(VLOOKUP(E24&$N$2&"Total",retroalimenación!D:F,3,0),"") -> 5 | O24: =ROUND(SUMPRODUCT(G24:H24,$G$1:$H$1)*4,1)+0.2 -> 5 | P24: =ROUND(SUMPRODUCT(I24:J24,$I$1:$J$1)*4,1)+0.4 -> 5 | Q24: =ROUND(SUMPRODUCT(K24:L24,$K$1:$L$1)*4,1) -> 5 | R24: =ROUND(SUMPRODUCT(M24:N24,$M$1:$N$1)*4,1) -> 5 | T24: =VLOOKUP(B24,bonificaciones!B:C,2,0) -> 0.6
A25: SÁNCHEZ ÁLVAREZ SEBASTIÁN | B25: sebastian.sanchez9@udea.edu.co | C25: 5 | D25: 5 | E25: 5 | F25: 5 | G25: 4.8 | H25: =IFERROR(VLOOKUP(C25&$H$2&"Total",retroalimenación!D:F,3,0),"") -> 5 | I25: 4.8 | J25: =IFERROR(VLOOKUP(D25&$J$2&"Total",retroalimenación!D:F,3,0),"") -> 4.275 | K25: 4.8 | L25: =IFERROR(VLOOKUP(E25&$L$2&"Total",retroalimenación!D:F,3,0),"") -> 5 | M25: 4.8 | N25: =IFERROR(VLOOKUP(E25&$N$2&"Total",retroalimenación!D:F,3,0),"") -> 5 | O25: =ROUND(SUMPRODUCT(G25:H25,$G$1:$H$1)*4,1) -> 4.9 | P25: =ROUND(SUMPRODUCT(I25:J25,$I$1:$J$1)*4,1) -> 4.5 | Q25: =ROUND(SUMPRODUCT(K25:L25,$K$1:$L$1)*4,1) -> 4.9 | R25: =ROUND(SUMPRODUCT(M25:N25,$M$1:$N$1)*4,1) -> 4.9 | S25: Sí | T25: =VLOOKUP(B25,bonificaciones!B:C,2,0) -> 0
A26: SOTO TABORDA JUAN ESTEBAN | B26: esteban.soto1@udea.edu.co | C26: 1 | D26: 1 | E26: 1 | F26: 1 | G26: =IFERROR(VLOOKUP(B26,seguimiento_HR!B:J,2,0),"") -> 4.8 | H26: =IFERROR(VLOOKUP(C26&$H$2&"Total",retroalimenación!D:F,3,0),"") -> 5 | I26: =IFERROR(VLOOKUP(B26,seguimiento_mark!B:C,2,0),"") -> 4 | J26: =IFERROR(VLOOKUP(D26&$J$2&"Total",retroalimenación!D:F,3,0),"") -> 5 | K26: =IFERROR(VLOOKUP(B26,seguimiento_salud!B:C,2,0),"") -> 3.9 | L26: =IFERROR(VLOOKUP(E26&$L$2&"Total",retroalimenación!D:F,3,0),"") -> 5 | M26: =IFERROR(VLOOKUP(B26,seguimiento_finanzas!B:C,2,0),"") -> 3.7 | N26: =IFERROR(VLOOKUP(E26&$N$2&"Total",retroalimenación!D:F,3,0),"") -> 5 | O26: =ROUND(SUMPRODUCT(G26:H26,$G$1:$H$1)*4,1) -> 4.9 | P26: =ROUND(SUMPRODUCT(I26:J26,$I$1:$J$1)*4,1)+0.4 -> 5 | Q26: =ROUND(SUMPRODUCT(K26:L26,$K$1:$L$1)*4,1) -> 4.6 | R26: =ROUND(SUMPRODUCT(M26:N26,$M$1:$N$1)*4,1) -> 4.5 | T26: =VLOOKUP(B26,bonificaciones!B:C,2,0) -> 0.4
A27: TORO VILLEGAS JUAN JOSE | B27: juanj.toro@udea.edu.co | C27: 7 | D27: 7 | E27: 7 | F27: 7 | G27: =IFERROR(VLOOKUP(B27,seguimiento_HR!B:J,2,0),"") -> 3.8 | H27: =IFERROR(VLOOKUP(C27&$H$2&"Total",retroalimenación!D:F,3,0),"") -> 3.9 | I27: =IFERROR(VLOOKUP(B27,seguimiento_mark!B:C,2,0),"") -> 3.8 | J27: =IFERROR(VLOOKUP(D27&$J$2&"Total",retroalimenación!D:F,3,0),"") -> 4.22 | K27: =IFERROR(VLOOKUP(B27,seguimiento_salud!B:C,2,0),"") -> 4.8 | L27: =IFERROR(VLOOKUP(E27&$L$2&"Total",retroalimenación!D:F,3,0),"") -> 4.325 | M27: =IFERROR(VLOOKUP(B27,seguimiento_finanzas!B:C,2,0),"") -> 2.1 | N27: =IFERROR(VLOOKUP(E27&$N$2&"Total",retroalimenación!D:F,3,0),"") -> 3.25 | O27: =ROUND(SUMPRODUCT(G27:H27,$G$1:$H$1)*4,1) -> 3.9 | P27: =ROUND(SUMPRODUCT(I27:J27,$I$1:$J$1)*4,1) -> 4.1 | Q27: =ROUND(SUMPRODUCT(K27:L27,$K$1:$L$1)*4,1) -> 4.5 | R27: =ROUND(SUMPRODUCT(M27:N27,$M$1:$N$1)*4,1) -> 2.8 | T27: =VLOOKUP(B27,bonificaciones!B:C,2,0) -> 0

Sheet grupos HR
A1: Grupo | B1: Correos | C1: Nombres | D1: Fecha anveces HR | E1: Fecha anveces marketing | F1: Grupo
A2: 1 | B2: alanis.alvarez@udea.edu.co | C2: Alanis Álvarez | D2: 45546 | F2: 1
A3: 1 | B3: esteban.soto1@udea.edu.co | C3: Juan Esteban Soto | D3: 45546 | F3: 1
A4: 1 | B4: santiago.restrepo23@udea.edu.co | C4: Santiago Restrepo | D4: 45546 | F4: 1
A5: 1 | B5: esteban.cardona6@udea.edu.co | C5: Juan Esteban Cardona | D5: 45546 | F5: 1
A6: 2 | B6: Manuela.blandon@udea.edu.co | C6: Manuela Blandón | D6: 45548 | F6: 2
A7: 2 | B7: Karen.perezc@udea.edu.co | C7: Karen Pérez Castilla | D7: 45548 | F7: 2
A8: 2 | B8: Dayana.delvalle@udea.edu.co | C8: Dayana Sofia del Valle | D8: 45548 | F8: 2
A9: 2 | B9: Alexander.amaya@udea.edu.co | C9: Alexander Amaya | D9: 45548 | F9: 2
A10: 3 | B10: laura.betancourt1@udea.edu.co | C10: Laura Betancourt | D10: 45548 | F10: 3
A11: 3 | B11: aura.molina@udea.edu.co | C11: Aura Molina | D11: 45548 | F11: 3
A12: 3 | B12: gilberto.gil1@udea.edu.co | C12: Gilberto Gil | D12: 45548 | F12: 3
A13: 4 | B13: osiris.contreras@udea.edu.co | C13: Osiris Contreras Trillos | D13: 45546 | F13: 4
A14: 4 | B14: gmaritza.zapata@udea.edu.co | C14: Maritza Zapata Gonzalez | D14: 45546 | E14: canceló | F14: 4
A15: 4 | B15: juanj.molina1@udea.edu.co | C15: Juan José Molina Ocampo | D15: 45546 | F15: 4
A16: 4 | B16: jfelipe.osorio@udea.edu.co | C16: Juan Felipe Osorio Lopez | D16: 45546 | F16: 4
A17: 5 | B17: Juan.arroyave14@udea.edu.co | C17: Juan Diego Arroyave Murillo | D17: 45546 | F17: 5
A18: 5 | B18: Sebastian.sanchez9@udea.edu.co | C18: Sebastian Sánchez Álvarez | D18: 45546 | F18: 5
A19: 5 | B19: estefania.dussan@udea.edu.co | C19: Estefanía Dussan Puerta | D19: 45546 | F19: 5
A20: 5 | B20: alejandro.alvarezl@udea.edu.co | C20: Alejandro Álvarez López | D20: 45546 | F20: 5
A21: 6 | B21: simon.marinz@udea.edu.co | C21: Simón Marín zuluaga | D21: 45546 | F21: 6
A22: 6 | B22: miguel.vargas1@udea.edu.co | C22: Miguel Ángel Vargas otalvaro | D22: 45546 | F22: 6
A23: 6 | B23: santiago.cordobac@udea.edu.co | C23: Santiago Córdoba Castañeda | D23: 45546 | F23: 6
A24: 7 | B24: natalia.guzmanz@udea.edu.co | C24: Natalia Guzman | D24: 45548 | F24: 7
A25: 7 | B25: sebastian.cuartas1@udea.edu.co | C25: Sebastian Cuartas | D25: 45548 | F25: 7
A26: 7 | B26: juanj.toro@udea.edu.co | C26: Juan José Toro Villegas | D26: 45548 | F26: 7
... A29: 8 | B29: leidys.guerrero@udea.edu.co | C29: Leidys Guerrero Lobo | D29: 45548 | F29: 8

Sheet seguimiento_HR
A2: Nombre | B2: Correo | C2: Total seguimiento | D2: Grupo 3 | E2: Grupo 4 | F2: 1. Identificación de necesidades | G2: 2. Diseño de la solución | H2: 3. Quiz artículo | I2: 4. Análisis de código | J2: 4. Presentación de avances HR | K2: 4. Presentación de avances HR | L2: Seguimientos
A3: CONTRERAS TRILLOS OSIRIS | B3: osiris.contreras@udea.edu.co | C3: =IFERROR(ROUND(AVERAGE(F3:K3),1),"") -> 4.5 | D3: =IFERROR(VLOOKUP(B3,consolidado_notas!B:C,2,0),"") -> 4 | E3: =D3 -> 4 | F3: =VLOOKUP(B3,seguimientos_extra!A:B,2,0) -> 4.5 | G3: =F3 -> 4.5 | H3: =G3 -> 4.5 | I3: =H3 -> 4.5 | J3: =IFERROR(ROUND(VLOOKUP(D3&$J$2&"Total",retroalimenación!D:F,3,0),1),"") -> 4.5 | K3: =J3 -> 4.5 | L3: =IFERROR(VLOOKUP(B3,seguimientos_extra!A:C,3,0),"") -> Sí
A4: OSORIO LÓPEZ JUAN FELIPE | B4: jfelipe.osorio@udea.edu.co | C4: =IFERROR(ROUND(AVERAGE(F4:K4),1),"") -> 4.8 | D4: =IFERROR(VLOOKUP(B4,consolidado_notas!B:C,2,0),"") -> 4 | E4: =D4 -> 4 | F4: =VLOOKUP(B4,seguimientos_extra!A:B,2,0) -> 5 | G4: =F4 -> 5 | H4: =G4 -> 5 | I4: =H4 -> 5 | J4: =IFERROR(ROUND(VLOOKUP(D4&$J$2&"Total",retroalimenación!D:F,3,0),1),"") -> 4.5 | K4: =J4 -> 4.5 | L4: =IFERROR(VLOOKUP(B4,seguimientos_extra!A:C,3,0),"") -> Sí
A5: ÁLVAREZ LÓPEZ ALEJANDRO | B5: alejandro.alvarezl@udea.edu.co | C5: =IFERROR(ROUND(AVERAGE(F5:K5),1),"") -> 4.6 | D5: =IFERROR(VLOOKUP(B5,consolidado_notas!B:C,2,0),"") -> 5 | E5: =D5 -> 5 | F5: =VLOOKUP(B5,seguimientos_extra!A:B,2,0) -> 4.7 | G5: =F5 -> 4.7 | H5: =G5 -> 4.7 | I5: =H5 -> 4.7 | J5: =IFERROR(ROUND(VLOOKUP(D5&$J$2&"Total",retroalimenación!D:F,3,0),1),"") -> 4.4 | K5: =J5 -> 4.4 | L5: =IFERROR(VLOOKUP(B5,seguimientos_extra!A:C,3,0),"") -> Sí
A6: ARROYAVE MURILLO JUAN DIEGO | B6: juan.arroyave14@udea.edu.co | C6: =IFERROR(ROUND(AVERAGE(F6:K6),1),"") -> 4.7 | D6: =IFERROR(VLOOKUP(B6,consolidado_notas!B:C,2,0),"") -> 5 | E6: =D6 -> 5 | F6: =VLOOKUP(B6,seguimientos_extra!A:B,2,0) -> 4.8 | G6: =F6 -> 4.8 | H6: =G6 -> 4.8 | I6: =H6 -> 4.8 | J6: =IFERROR(ROUND(VLOOKUP(D6&$J$2&"Total",retroalimenación!D:F,3,0),1),"") -> 4.4 | K6: =J6 -> 4.4 | L6: =IFERROR(VLOOKUP(B6,seguimientos_extra!A:C,3,0),"") -> Sí
A7: DUSSAN PUERTA ESTEFANIA | B7: estefania.dussan@udea.edu.co | C7: =IFERROR(ROUND(AVERAGE(F7:K7),1),"") -> 4.8 | D7: =IFERROR(VLOOKUP(B7,consolidado_notas!B:C,2,0),"") -> 5 | E7: =D7 -> 5 | F7: =VLOOKUP(B7,seguimientos_extra!A:B,2,0) -> 5 | G7: =F7 -> 5 | H7: =G7 -> 5 | I7: =H7 -> 5 | J7: =IFERROR(ROUND(VLOOKUP(D7&$J$2&"Total",retroalimenación!D:F,3,0),1),"") -> 4.4 | K7: =J7 -> 4.4 | L7: =IFERROR(VLOOKUP(B7,seguimientos_extra!A:C,3,0),"") -> Sí
A8: SÁNCHEZ ÁLVAREZ SEBASTIÁN | B8: sebastian.sanchez9@udea.edu.co | C8: =IFERROR(ROUND(AVERAGE(F8:K8),1),"") -> 4.7 | D8: =IFERROR(VLOOKUP(B8,consolidado_notas!B:C,2,0),"") -> 5 | E8: =D8 -> 5 | F8: =VLOOKUP(B8,seguimientos_extra!A:B,2,0) -> 4.8 | G8: =F8 -> 4.8 | H8: =G8 -> 4.8 | I8: =H8 -> 4.8 | J8: =IFERROR(ROUND(VLOOKUP(D8&$J$2&"Total",retroalimenación!D:F,3,0),1),"") -> 4.4 | K8: =J8 -> 4.4 | L8: =IFERROR(VLOOKUP(B8,seguimientos_extra!A:C,3,0),"") -> Sí
A9: ARABIA ÁLVAREZ PAOLA ANDREA | B9: paola.arabia@udea.edu.co | C9: =IFERROR(ROUND(AVERAGE(F9:K9),1),"") -> 4.2 | D9: =IFERROR(VLOOKUP(B9,consolidado_notas!B:C,2,0),"") -> 8 | E9: =D9 -> 8 | F9: =VLOOKUP(B9,seguimientos_extra!A:B,2,0) -> 4.5 | G9: =F9 -> 4.5 | H9: =G9 -> 4.5 | I9: =H9 -> 4.5 | J9: =IFERROR(ROUND(VLOOKUP(D9&$J$2&"Total",retroalimenación!D:F,3,0),1),"") -> 3.5 | K9: =J9 -> 3.5 | L9: =IFERROR(VLOOKUP(B9,seguimientos_extra!A:C,3,0),"") -> Sí
A10: GUERRERO LOBO LEIDYS | B10: leidys.guerrero@udea.edu.co | C10: =IFERROR(ROUND(AVERAGE(F10:K10),1),"") -> 4.1 | D10: =IFERROR(VLOOKUP(B10,consolidado_notas!B:C,2,0),"") -> 8 | E10: =D10 -> 8 | F10: =VLOOKUP(B10,seguimientos_extra!A:B,2,0) -> 4.4 | G10: =F10 -> 4.4 | H10: =G10 -> 4.4 | I10: =H10 -> 4.4 | J10: =IFERROR(ROUND(VLOOKUP(D10&$J$2&"Total",retroalimenación!D:F,3,0),1),"") -> 3.5 | K10: =J10 -> 3.5 | L10: =IFERROR(VLOOKUP(B10,seguimientos_extra!A:C,3,0),"") -> Sí
A11: ALVAREZ FERNANDEZ ALANIS | B11: alanis.alvarez@udea.edu.co | C11: =IFERROR(ROUND(AVERAGE(F11:K11),1),"") -> 4.6 | D11: =IFERROR(VLOOKUP(B11,consolidado_notas!B:C,2,0),"") -> 1 | E11: =D11 -> 1 | F11: 5 | G11: 5 | H11: 3.7 | I11: 5 | J11: =IFERROR(ROUND(VLOOKUP(D11&$J$2&"Total",retroalimenación!D:F,3,0),1),"") -> 4.5 | K11: =J11 -> 4.5 | L11: =IFERROR(VLOOKUP(B11,seguimientos_extra!A:C,3,0),"")
A12: CARDONA MOLINA JUAN ESTEBAN | B12: esteban.cardona6@udea.edu.co | C12: =IFERROR(ROUND(AVERAGE(F12:K12),1),"") -> 4.8 | D12: =IFERROR(VLOOKUP(B12,consolidado_notas!B:C,2,0),"") -> 1 | E12: =D12 -> 1 | F12: 5 | G12: 5 | H12: 5 | I12: 5 | J12: =IFERROR(ROUND(VLOOKUP(D12&$J$2&"Total",retroalimenación!D:F,3,0),1),"") -> 4.5 | K12: =J12 -> 4.5 | L12: =IFERROR(VLOOKUP(B12,seguimientos_extra!A:C,3,0),"")
A13: RESTREPO OLARTE SANTIAGO | B13: santiago.restrepo23@udea.edu.co | C13: =IFERROR(ROUND(AVERAGE(F13:K13),1),"") -> 4.6 | D13: =IFERROR(VLOOKUP(B13,consolidado_notas!B:C,2,0),"") -> 1 | E13: =D13 -> 1 | F13: 5 | G13: 5 | H13: 3.7 | I13: 5 | J13: =IFERROR(ROUND(VLOOKUP(D13&$J$2&"Total",retroalimenación!D:F,3,0),1),"") -> 4.5 | K13: =J13 -> 4.5 | L13: =IFERROR(VLOOKUP(B13,seguimientos_extra!A:C,3,0),"")
A14: SOTO TABORDA JUAN ESTEBAN | B14: esteban.soto1@udea.edu.co | C14: =IFERROR(ROUND(AVERAGE(F14:K14),1),"") -> 4.8 | D14: =IFERROR(VLOOKUP(B14,consolidado_notas!B:C,2,0),"") -> 1 | E14: =D14 -> 1 | F14: 5 | G14: 5 | H14: 4.7 | I14: 5 | J14: =IFERROR(ROUND(VLOOKUP(D14&$J$2&"Total",retroalimenación!D:F,3,0),1),"") -> 4.5 | K14: =J14 -> 4.5 | L14: =IFERROR(VLOOKUP(B14,seguimientos_extra!A:C,3,0),"")
A15: AMAYA LEÓN ALEXÁNDER | B15: alexander.amaya@udea.edu.co | C15: =IFERROR(ROUND(AVERAGE(F15:K15),1),"") -> 4.1 | D15: =IFERROR(VLOOKUP(B15,consolidado_notas!B:C,2,0),"") -> 2 | E15: =D15 -> 2 | F15: 5 | G15: 0 | H15: 4.7 | I15: 5 | J15: =IFERROR(ROUND(VLOOKUP(D15&$J$2&"Total",retroalimenación!D:F,3,0),1),"") -> 4.8 | K15: =J15 -> 4.8 | L15: =IFERROR(VLOOKUP(B15,seguimientos_extra!A:C,3,0),"")
A16: BLANDÓN RAMÍREZ MANUELA | B16: manuela.blandon@udea.edu.co | C16: =IFERROR(ROUND(AVERAGE(F16:K16),1),"") -> 4.6 | D16: =IFERROR(VLOOKUP(B16,consolidado_notas!B:C,2,0),"") -> 2 | E16: =D16 -> 2 | F16: 5 | G16: 5 | H16: 2.7 | I16: 5 | J16: =IFERROR(ROUND(VLOOKUP(D16&$J$2&"Total",retroalimenación!D:F,3,0),1),"") -> 4.8 | K16: =J16 -> 4.8 | L16: =IFERROR(VLOOKUP(B16,seguimientos_extra!A:C,3,0),"")
A17: DEL VALLE CORREA DAYANA SOFIA | B17: dayana.delvalle@udea.edu.co | C17: =IFERROR(ROUND(AVERAGE(F17:K17),1),"") -> 4.7 | D17: =IFERROR(VLOOKUP(B17,consolidado_notas!B:C,2,0),"") -> 2 | E17: =D17 -> 2 | F17: 5 | G17: 5 | H17: 3.7 | I17: 5 | J17: =IFERROR(ROUND(VLOOKUP(D17&$J$2&"Total",retroalimenación!D:F,3,0),1),"") -> 4.8 | K17: =J17 -> 4.8 | L17: =IFERROR(VLOOKUP(B17,seguimientos_extra!A:C,3,0),"")
A18: PEREZ CASTILLA KAREN MARCELA | B18: karen.perezc@udea.edu.co | C18: =IFERROR(ROUND(AVERAGE(F18:K18),1),"") -> 4.7 | D18: =IFERROR(VLOOKUP(B18,consolidado_notas!B:C,2,0),"") -> 2 | E18: =D18 -> 2 | F18: 5 | H18: 4 | I18: 5 | J18: =IFERROR(ROUND(VLOOKUP(D18&$J$2&"Total",retroalimenación!D:F,3,0),1),"") -> 4.8 | K18: =J18 -> 4.8 | L18: =IFERROR(VLOOKUP(B18,seguimientos_extra!A:C,3,0),"")
A19: BETANCOURT FUENTES LAURA CAMILA | B19: laura.betancourt1@udea.edu.co | C19: =IFERROR(ROUND(AVERAGE(F19:K19),1),"") -> 4.4 | D19: =IFERROR(VLOOKUP(B19,consolidado_notas!B:C,2,0),"") -> 3 | E19: =D19 -> 3 | F19: 5 | H19: 4 | I19: 5 | J19: =IFERROR(ROUND(VLOOKUP(D19&$J$2&"Total",retroalimenación!D:F,3,0),1),"") -> 4 | K19: =J19 -> 4 | L19: =IFERROR(VLOOKUP(B19,seguimientos_extra!A:C,3,0),"")
A20: GIL PACHECO GILBERTO JOSÉ | B20: gilberto.gil1@udea.edu.co | C20: =IFERROR(ROUND(AVERAGE(F20:K20),1),"") -> 4.5 | D20: =IFERROR(VLOOKUP(B20,consolidado_notas!B:C,2,0),"") -> 3 | E20: =D20 -> 3 | F20: 5 | G20: 5 | H20: 3.8 | I20: 5 | J20: =IFERROR(ROUND(VLOOKUP(D20&$J$2&"Total",retroalimenación!D:F,3,0),1),"") -> 4 | K20: =J20 -> 4 | L20: =IFERROR(VLOOKUP(B20,seguimientos_extra!A:C,3,0),"")
A21: MOLINA AMAYA AURA MARÍA | B21: aura.molina@udea.edu.co | C21: =IFERROR(ROUND(AVERAGE(F21:K21),1),"") -> 3 | D21: =IFERROR(VLOOKUP(B21,consolidado_notas!B:C,2,0),"") -> 3 | E21: =D21 -> 3 | F21: 5 | G21: 0 | H21: 5 | I21: 0 | J21: =IFERROR(ROUND(VLOOKUP(D21&$J$2&"Total",retroalimenación!D:F,3,0),1),"") -> 4 | K21: =J21 -> 4 | L21: =IFERROR(VLOOKUP(B21,seguimientos_extra!A:C,3,0),"")
A22: MOLINA OCAMPO JUAN JOSE | B22: juanj.molina1@udea.edu.co | C22: =IFERROR(ROUND(AVERAGE(F22:K22),1),"") -> 4.4 | D22: =IFERROR(VLOOKUP(B22,consolidado_notas!B:C,2,0),"") -> 4 | E22: =D22 -> 4 | F22: 5 | H22: 3 | I22: 5 | J22: =IFERROR(ROUND(VLOOKUP(D22&$J$2&"Total",retroalimenación!D:F,3,0),1),"") -> 4.5 | K22: =J22 -> 4.5 | L22: =IFERROR(VLOOKUP(B22,seguimientos_extra!A:C,3,0),"")
A23: MARIN ZULUAGA SIMON | B23: simon.marinz@udea.edu.co | C23: =IFERROR(ROUND(AVERAGE(F23:K23),1),"") -> 4.3 | D23: =IFERROR(VLOOKUP(B23,consolidado_notas!B:C,2,0),"") -> 6 | E23: =D23 -> 6 | F23: 5 | G23: 5 | H23: 2.3 | I23: 5 | J23: =IFERROR(ROUND(VLOOKUP(D23&$J$2&"Total",retroalimenación!D:F,3,0),1),"") -> 4.3 | K23: =J23 -> 4.3 | L23: =IFERROR(VLOOKUP(B23,seguimientos_extra!A:C,3,0),"")
A24: CAICEDO AGUIRRE MATEO | B24: mateo.caicedo@udea.edu.co | C24: =IFERROR(ROUND(AVERAGE(F24:K24),1),"") -> 4.5 | D24: =IFERROR(VLOOKUP(B24,consolidado_notas!B:C,2,0),"") -> 7 | E24: =D24 -> 7 | F24: 5 | G24: 5 | H24: 4 | I24: 5 | J24: =IFERROR(ROUND(VLOOKUP(D24&$J$2&"Total",retroalimenación!D:F,3,0),1),"") -> 4.1 | K24: =J24 -> 4.1 | L24: =IFERROR(VLOOKUP(B24,seguimientos_extra!A:C,3,0),"")
A25: CUARTAS GIL SEBASTIAN | B25: sebastian.cuartas1@udea.edu.co | C25: =IFERROR(ROUND(AVERAGE(F25:K25),1),"") -> 4.5 | D25: =IFERROR(VLOOKUP(B25,consolidado_notas!B:C,2,0),"") -> 7 | E25: =D25 -> 7 | F25: 5 | G25: 5 | H25: 4 | I25: 5 | J25: =IFERROR(ROUND(VLOOKUP(D25&$J$2&"Total",retroalimenación!D:F,3,0),1),"") -> 4.1 | K25: =J25 -> 4.1 | L25: =IFERROR(VLOOKUP(B25,seguimientos_extra!A:C,3,0),"")
A26: GUZMAN ZORRILLA NATALIA XIMENA | B26: natalia.guzmanz@udea.edu.co | C26: =IFERROR(ROUND(AVERAGE(F26:K26),1),"") -> 4.3 | D26: =IFERROR(VLOOKUP(B26,consolidado_notas!B:C,2,0),"") -> 7 | E26: =D26 -> 7 | F26: 5 | G26: 5 | H26: 2.3 | I26: 5 | J26: =IFERROR(ROUND(VLOOKUP(D26&$J$2&"Total",retroalimenación!D:F,3,0),1),"") -> 4.1 | K26: =J26 -> 4.1 | L26: =IFERROR(VLOOKUP(B26,seguimientos_extra!A:C,3,0),"")
A27: TORO VILLEGAS JUAN JOSE | B27: juanj.toro@udea.edu.co | C27: =IFERROR(ROUND(AVERAGE(F27:K27),1),"") -> 3.8 | D27: =IFERROR(VLOOKUP(B27,consolidado_notas!B:C,2,0),"") -> 7 | E27: =D27 -> 7 | F27: 5 | G27: 0 | H27: 4.7 | I27: 5 | J27: =IFERROR(ROUND(VLOOKUP(D27&$J$2&"Total",retroalimenación!D:F,3,0),1),"") -> 4.1 | K27: =J27 -> 4.1 | L27: =IFERROR(VLOOKUP(B27,seguimientos_extra!A:C,3,0),"")

Sheet seguimiento_mark
A2: Nombre | B2: Correo | C2: Total seguimiento con bonificación | D2: Grupo 3 | E2: 1. solucioes analíticas famosas | F2: 2.Sql | G2: 3. Ejercicio con sistemas de recomendación | H2: 4. Presentación de avances mark | I2: 4. Presentación de avances mark | J2: Seguimientos
A3: OSORIO LÓPEZ JUAN FELIPE | B3: jfelipe.osorio@udea.edu.co | C3: =IFERROR(ROUND(AVERAGE(E3:I3),1),"") -> 4.9 | D3: =IFERROR(VLOOKUP(B3,consolidado_notas!B:D,3,0),"") -> 4 | E3: =VLOOKUP(B3,seguimientos_extra!A:B,2,0) -> 5 | F3: =E3 -> 5 | G3: =F3 -> 5 | H3: =IFERROR(ROUND(VLOOKUP(D3&$I$2&"Total",retroalimenación!D:F,3,0),1),"") -> 4.7 | I3: =H3 -> 4.7 | J3: =IFERROR(VLOOKUP(B3,seguimientos_extra!A:C,3,0),"") -> Sí
A4: ÁLVAREZ LÓPEZ ALEJANDRO | B4: alejandro.alvarezl@udea.edu.co | C4: =IFERROR(ROUND(AVERAGE(E4:I4),1),"") -> 2.8 | D4: =IFERROR(VLOOKUP(B4,consolidado_notas!B:D,3,0),"") -> 5 | E4: =VLOOKUP(B4,seguimientos_extra!A:B,2,0) -> 4.7 | F4: =E4 -> 4.7 | G4: =F4 -> 4.7 | H4: =IFERROR(ROUND(VLOOKUP(D4&$I$2&"Total",retroalimenación!D:F,3,0),1),"") -> 0 | I4: =H4 -> 0 | J4: =IFERROR(VLOOKUP(B4,seguimientos_extra!A:C,3,0),"") -> Sí
A5: ARABIA ÁLVAREZ PAOLA ANDREA | B5: paola.arabia@udea.edu.co | C5: =IFERROR(ROUND(AVERAGE(E5:I5),1),"") -> 4.3 | D5: =IFERROR(VLOOKUP(B5,consolidado_notas!B:D,3,0),"") -> 8 | E5: =VLOOKUP(B5,seguimientos_extra!A:B,2,0) -> 4.5 | F5: =E5 -> 4.5 | G5: =F5 -> 4.5 | H5: =IFERROR(ROUND(VLOOKUP(D5&$I$2&"Total",retroalimenación!D:F,3,0),1),"") -> 4.1 | I5: =H5 -> 4.1 | J5: =IFERROR(VLOOKUP(B5,seguimientos_extra!A:C,3,0),"") -> Sí
A6: ARROYAVE MURILLO JUAN DIEGO | B6: juan.arroyave14@udea.edu.co | C6: =IFERROR(ROUND(AVERAGE(E6:I6),1),"") -> 2.9 | D6: =IFERROR(VLOOKUP(B6,consolidado_notas!B:D,3,0),"") -> 5 | E6: =VLOOKUP(B6,seguimientos_extra!A:B,2,0) -> 4.8 | F6: =E6 -> 4.8 | G6: =F6 -> 4.8 | H6: =IFERROR(ROUND(VLOOKUP(D6&$I$2&"Total",retroalimenación!D:F,3,0),1),"") -> 0 | I6: =H6 -> 0 | J6: =IFERROR(VLOOKUP(B6,seguimientos_extra!A:C,3,0),"") -> Sí
A7: CONTRERAS TRILLOS OSIRIS | B7: osiris.contreras@udea.edu.co | C7: =IFERROR(ROUND(AVERAGE(E7:I7),1),"") -> 4.6 | D7: =IFERROR(VLOOKUP(B7,consolidado_notas!B:D,3,0),"") -> 4 | E7: =VLOOKUP(B7,seguimientos_extra!A:B,2,0) -> 4.5 | F7: =E7 -> 4.5 | G7: =F7 -> 4.5 | H7: =IFERROR(ROUND(VLOOKUP(D7&$I$2&"Total",retroalimenación!D:F,3,0),1),"") -> 4.7 | I7: =H7 -> 4.7 | J7: =IFERROR(VLOOKUP(B7,seguimientos_extra!A:C,3,0),"") -> Sí
A8: DUSSAN PUERTA ESTEFANIA | B8: estefania.dussan@udea.edu.co | C8: =IFERROR(ROUND(AVERAGE(E8:I8),1),"") -> 3 | D8: =IFERROR(VLOOKUP(B8,consolidado_notas!B:D,3,0),"") -> 5 | E8: =VLOOKUP(B8,seguimientos_extra!A:B,2,0) -> 5 | F8: =E8 -> 5 | G8: =F8 -> 5 | H8: =IFERROR(ROUND(VLOOKUP(D8&$I$2&"Total",retroalimenación!D:F,3,0),1),"") -> 0 | I8: =H8 -> 0 | J8: =IFERROR(VLOOKUP(B8,seguimientos_extra!A:C,3,0),"") -> Sí
A9: GUERRERO LOBO LEIDYS | B9: leidys.guerrero@udea.edu.co | C9: =IFERROR(ROUND(AVERAGE(E9:I9),1),"") -> 4.3 | D9: =IFERROR(VLOOKUP(B9,consolidado_notas!B:D,3,0),"") -> 8 | E9: =VLOOKUP(B9,seguimientos_extra!A:B,2,0) -> 4.4 | F9: =E9 -> 4.4 | G9: =F9 -> 4.4 | H9: =IFERROR(ROUND(VLOOKUP(D9&$I$2&"Total",retroalimenación!D:F,3,0),1),"") -> 4.1 | I9: =H9 -> 4.1 | J9: =IFERROR(VLOOKUP(B9,seguimientos_extra!A:C,3,0),"") -> Sí
A10: SÁNCHEZ ÁLVAREZ SEBASTIÁN | B10: sebastian.sanchez9@udea.edu.co | C10: =IFERROR(ROUND(AVERAGE(E10:I10),1),"") -> 2.9 | D10: =IFERROR(VLOOKUP(B10,consolidado_notas!B:D,3,0),"") -> 5 | E10: =VLOOKUP(B10,seguimientos_extra!A:B,2,0) -> 4.8 | F10: =E10 -> 4.8 | G10: =F10 -> 4.8 | H10: =IFERROR(ROUND(VLOOKUP(D10&$I$2&"Total",retroalimenación!D:F,3,0),1),"") -> 0 | I10: =H10 -> 0 | J10: =IFERROR(VLOOKUP(B10,seguimientos_extra!A:C,3,0),"") -> Sí
A11: ALVAREZ FERNANDEZ ALANIS | B11: alanis.alvarez@udea.edu.co | C11: =IFERROR(ROUND(AVERAGE(E11:I11),1),"") -> 3 | D11: =IFERROR(VLOOKUP(B11,consolidado_notas!B:D,3,0),"") -> 1 | E11: 0 | F11: 0 | G11: 5 | H11: =IFERROR(ROUND(VLOOKUP(D11&$I$2&"Total",retroalimenación!D:F,3,0),1),"") -> 5 | I11: =H11 -> 5 | J11: =IFERROR(VLOOKUP(B11,seguimientos_extra!A:C,3,0),"")
A12: BETANCOURT FUENTES LAURA CAMILA | B12: laura.betancourt1@udea.edu.co | C12: =IFERROR(ROUND(AVERAGE(E12:I12),1),"") -> 4.8 | D12: =IFERROR(VLOOKUP(B12,consolidado_notas!B:D,3,0),"") -> 3 | E12: 5 | F12: 5 | G12: 5 | H12: =IFERROR(ROUND(VLOOKUP(D12&$I$2&"Total",retroalimenación!D:F,3,0),1),"") -> 4.5 | I12: =H12 -> 4.5 | J12: =IFERROR(VLOOKUP(B12,seguimientos_extra!A:C,3,0),"")
A13: BLANDÓN RAMÍREZ MANUELA | B13: manuela.blandon@udea.edu.co | C13: =IFERROR(ROUND(AVERAGE(E13:I13),1),"") -> 5 | D13: =IFERROR(VLOOKUP(B13,consolidado_notas!B:D,3,0),"") -> 2 | E13: 5 | F13: 5 | G13: 5 | H13: =IFERROR(ROUND(VLOOKUP(D13&$I$2&"Total",retroalimenación!D:F,3,0),1),"") -> 5 | I13: =H13 -> 5 | J13: =IFERROR(VLOOKUP(B13,seguimientos_extra!A:C,3,0),"")
A14: CARDONA MOLINA JUAN ESTEBAN | B14: esteban.cardona6@udea.edu.co | C14: =IFERROR(ROUND(AVERAGE(E14:I14),1),"") -> 5 | D14: =IFERROR(VLOOKUP(B14,consolidado_notas!B:D,3,0),"") -> 1 | E14: 5 | F14: 5 | G14: 5 | H14: =IFERROR(ROUND(VLOOKUP(D14&$I$2&"Total",retroalimenación!D:F,3,0),1),"") -> 5 | I14: =H14 -> 5 | J14: =IFERROR(VLOOKUP(B14,seguimientos_extra!A:C,3,0),"")
A15: CUARTAS GIL SEBASTIAN | B15: sebastian.cuartas1@udea.edu.co | C15: =IFERROR(ROUND(AVERAGE(E15:I15),1),"") -> 3.8 | D15: =IFERROR(VLOOKUP(B15,consolidado_notas!B:D,3,0),"") -> 7 | E15: 5 | F15: 0 | G15: 5 | H15: =IFERROR(ROUND(VLOOKUP(D15&$I$2&"Total",retroalimenación!D:F,3,0),1),"") -> 4.4 | I15: =H15 -> 4.4 | J15: =IFERROR(VLOOKUP(B15,seguimientos_extra!A:C,3,0),"")
A16: PEREZ CASTILLA KAREN MARCELA | B16: karen.perezc@udea.edu.co | C16: =IFERROR(ROUND(AVERAGE(E16:I16),1),"") -> 5 | D16: =IFERROR(VLOOKUP(B16,consolidado_notas!B:D,3,0),"") -> 2 | E16: 5 | F16: 5 | G16: 5 | H16: =IFERROR(ROUND(VLOOKUP(D16&$I$2&"Total",retroalimenación!D:F,3,0),1),"") -> 5 | I16: =H16 -> 5 | J16: =IFERROR(VLOOKUP(B16,seguimientos_extra!A:C,3,0),"")
A17: SOTO TABORDA JUAN ESTEBAN | B17: esteban.soto1@udea.edu.co | C17: =IFERROR(ROUND(AVERAGE(E17:I17),1),"") -> 4 | D17: =IFERROR(VLOOKUP(B17,consolidado_notas!B:D,3,0),"") -> 1 | E17: 5 | F17: 0 | G17: 5 | H17: =IFERROR(ROUND(VLOOKUP(D17&$I$2&"Total",retroalimenación!D:F,3,0),1),"") -> 5 | I17: =H17 -> 5 | J17: =IFERROR(VLOOKUP(B17,seguimientos_extra!A:C,3,0),"")
A18: TORO VILLEGAS JUAN JOSE | B18: juanj.toro@udea.edu.co | C18: =IFERROR(ROUND(AVERAGE(E18:I18),1),"") -> 3.8 | D18: =IFERROR(VLOOKUP(B18,consolidado_notas!B:D,3,0),"") -> 7 | E18: 5 | F18: 0 | G18: 5 | H18: =IFERROR(ROUND(VLOOKUP(D18&$I$2&"Total",retroalimenación!D:F,3,0),1),"") -> 4.4 | I18: =H18 -> 4.4 | J18: =IFERROR(VLOOKUP(B18,seguimientos_extra!A:C,3,0),"")
A19: AMAYA LEÓN ALEXÁNDER | B19: alexander.amaya@udea.edu.co | C19: =IFERROR(ROUND(AVERAGE(E19:I19),1),"") -> 2 | D19: =IFERROR(VLOOKUP(B19,consolidado_notas!B:D,3,0),"") -> 2 | E19: 0 | F19: 0 | G19: 0 | H19: =IFERROR(ROUND(VLOOKUP(D19&$I$2&"Total",retroalimenación!D:F,3,0),1),"") -> 5 | I19: =H19 -> 5 | J19: =IFERROR(VLOOKUP(B19,seguimientos_extra!A:C,3,0),"")
A20: CAICEDO AGUIRRE MATEO | B20: mateo.caicedo@udea.edu.co | C20: =IFERROR(ROUND(AVERAGE(E20:I20),1),"") -> 2.6 | D20: =IFERROR(VLOOKUP(B20,consolidado_notas!B:D,3,0),"") -> 8 | E20: 0 | F20: 5 | G20: 0 | H20: =IFERROR(ROUND(VLOOKUP(D20&$I$2&"Total",retroalimenación!D:F,3,0),1),"") -> 4.1 | I20: =H20 -> 4.1 | J20: =IFERROR(VLOOKUP(B20,seguimientos_extra!A:C,3,0),"")
A21: DEL VALLE CORREA DAYANA SOFIA | B21: dayana.delvalle@udea.edu.co | C21: =IFERROR(ROUND(AVERAGE(E21:I21),1),"") -> 4 | D21: =IFERROR(VLOOKUP(B21,consolidado_notas!B:D,3,0),"") -> 2 | E21: 5 | F21: 5 | G21: 0 | H21: =IFERROR(ROUND(VLOOKUP(D21&$I$2&"Total",retroalimenación!D:F,3,0),1),"") -> 5 | I21: =H21 -> 5 | J21: =IFERROR(VLOOKUP(B21,seguimientos_extra!A:C,3,0),"")
A22: GIL PACHECO GILBERTO JOSÉ | B22: gilberto.gil1@udea.edu.co | C22: =IFERROR(ROUND(AVERAGE(E22:I22),1),"") -> 3.8 | D22: =IFERROR(VLOOKUP(B22,consolidado_notas!B:D,3,0),"") -> 3 | E22: 5 | F22: 5 | G22: 0 | H22: =IFERROR(ROUND(VLOOKUP(D22&$I$2&"Total",retroalimenación!D:F,3,0),1),"") -> 4.5 | I22: =H22 -> 4.5 | J22: =IFERROR(VLOOKUP(B22,seguimientos_extra!A:C,3,0),"")
... A27: RESTREPO OLARTE SANTIAGO | B27: santiago.restrepo23@udea.edu.co | C27: =IFERROR(ROUND(AVERAGE(E27:I27),1),"") -> 4 | D27: =IFERROR(VLOOKUP(B27,consolidado_notas!B:D,3,0),"") -> 1 | E27: 5 | F27: 5 | G27: 0 | H27: =IFERROR(ROUND(VLOOKUP(D27&$I$2&"Total",retroalimenación!D:F,3,0),1),"") -> 5 | I27: =H27 -> 5 | J27: =IFERROR(VLOOKUP(B27,seguimientos_extra!A:C,3,0),"")

Sheet seguimiento_salud
A2: Nombre | B2: Correo | C2: Total seguimiento con bonificación | D2: Grupo 1 | E2: 1. Diseño solución problema propuesto | F2: 2. Artículo | G2: 3. Prediccion imágenes | H2: 4. Presentación avances salud | I2: 4. Presentación avances salud | J2: Seguimientos
A3: ÁLVAREZ LÓPEZ ALEJANDRO | B3: alejandro.alvarezl@udea.edu.co | C3: =IFERROR(ROUND(AVERAGE(E3:I3),1),"") -> 4.6 | D3: =VLOOKUP(B3,consolidado_notas!B:E,4,0) -> 5 | E3: =VLOOKUP(B3,seguimientos_extra!A:B,2,0) -> 4.7 | F3: =E3 -> 4.7 | G3: =F3 -> 4.7 | H3: =IFERROR(VLOOKUP(D3&H$2&"Total",retroalimenación!D:F,3,0),"") -> 4.4 | I3: =H3 -> 4.4 | J3: =IFERROR(VLOOKUP(B3,seguimientos_extra!A:C,3,0),"") -> Sí
A4: ARABIA ÁLVAREZ PAOLA ANDREA | B4: paola.arabia@udea.edu.co | C4: =IFERROR(ROUND(AVERAGE(E4:I4),1),"") -> 4.5 | D4: =VLOOKUP(B4,consolidado_notas!B:E,4,0) -> 8 | E4: =VLOOKUP(B4,seguimientos_extra!A:B,2,0) -> 4.5 | F4: =E4 -> 4.5 | G4: =F4 -> 4.5 | H4: =IFERROR(VLOOKUP(D4&H$2&"Total",retroalimenación!D:F,3,0),"") -> 4.4 | I4: =H4 -> 4.4 | J4: =IFERROR(VLOOKUP(B4,seguimientos_extra!A:C,3,0),"") -> Sí
A5: ARROYAVE MURILLO JUAN DIEGO | B5: juan.arroyave14@udea.edu.co | C5: =IFERROR(ROUND(AVERAGE(E5:I5),1),"") -> 4.6 | D5: =VLOOKUP(B5,consolidado_notas!B:E,4,0) -> 5 | E5: =VLOOKUP(B5,seguimientos_extra!A:B,2,0) -> 4.8 | F5: =E5 -> 4.8 | G5: =F5 -> 4.8 | H5: =IFERROR(VLOOKUP(D5&H$2&"Total",retroalimenación!D:F,3,0),"") -> 4.4 | I5: =H5 -> 4.4 | J5: =IFERROR(VLOOKUP(B5,seguimientos_extra!A:C,3,0),"") -> Sí
A6: CONTRERAS TRILLOS OSIRIS | B6: osiris.contreras@udea.edu.co | C6: =IFERROR(ROUND(AVERAGE(E6:I6),1),"") -> 4.5 | D6: =VLOOKUP(B6,consolidado_notas!B:E,4,0) -> 4 | E6: =VLOOKUP(B6,seguimientos_extra!A:B,2,0) -> 4.5 | F6: =E6 -> 4.5 | G6: =F6 -> 4.5 | H6: =IFERROR(VLOOKUP(D6&H$2&"Total",retroalimenación!D:F,3,0),"") -> 4.4 | I6: =H6 -> 4.4 | J6: =IFERROR(VLOOKUP(B6,seguimientos_extra!A:C,3,0),"") -> Sí
A7: OSORIO LÓPEZ JUAN FELIPE | B7: jfelipe.osorio@udea.edu.co | C7: =IFERROR(ROUND(AVERAGE(E7:I7),1),"") -> 4.8 | D7: =VLOOKUP(B7,consolidado_notas!B:E,4,0) -> 4 | E7: =VLOOKUP(B7,seguimientos_extra!A:B,2,0) -> 5 | F7: =E7 -> 5 | G7: =F7 -> 5 | H7: =IFERROR(VLOOKUP(D7&H$2&"Total",retroalimenación!D:F,3,0),"") -> 4.4 | I7: =H7 -> 4.4 | J7: =IFERROR(VLOOKUP(B7,seguimientos_extra!A:C,3,0),"") -> Sí
A8: DUSSAN PUERTA ESTEFANIA | B8: estefania.dussan@udea.edu.co | C8: =IFERROR(ROUND(AVERAGE(E8:I8),1),"") -> 4.8 | D8: =VLOOKUP(B8,consolidado_notas!B:E,4,0) -> 5 | E8: =VLOOKUP(B8,seguimientos_extra!A:B,2,0) -> 5 | F8: =E8 -> 5 | G8: =F8 -> 5 | H8: =IFERROR(VLOOKUP(D8&H$2&"Total",retroalimenación!D:F,3,0),"") -> 4.4 | I8: =H8 -> 4.4 | J8: =IFERROR(VLOOKUP(B8,seguimientos_extra!A:C,3,0),"") -> Sí
A9: GUERRERO LOBO LEIDYS | B9: leidys.guerrero@udea.edu.co | C9: =IFERROR(ROUND(AVERAGE(E9:I9),1),"") -> 4.4 | D9: =VLOOKUP(B9,consolidado_notas!B:E,4,0) -> 8 | E9: =VLOOKUP(B9,seguimientos_extra!A:B,2,0) -> 4.4 | F9: =E9 -> 4.4 | G9: =F9 -> 4.4 | H9: =IFERROR(VLOOKUP(D9&H$2&"Total",retroalimenación!D:F,3,0),"") -> 4.4 | I9: =H9 -> 4.4 | J9: =IFERROR(VLOOKUP(B9,seguimientos_extra!A:C,3,0),"") -> Sí
A10: SÁNCHEZ ÁLVAREZ SEBASTIÁN | B10: sebastian.sanchez9@udea.edu.co | C10: =IFERROR(ROUND(AVERAGE(E10:I10),1),"") -> 4.6 | D10: =VLOOKUP(B10,consolidado_notas!B:E,4,0) -> 5 | E10: =VLOOKUP(B10,seguimientos_extra!A:B,2,0) -> 4.8 | F10: =E10 -> 4.8 | G10: =F10 -> 4.8 | H10: =IFERROR(VLOOKUP(D10&H$2&"Total",retroalimenación!D:F,3,0),"") -> 4.4 | I10: =H10 -> 4.4 | J10: =IFERROR(VLOOKUP(B10,seguimientos_extra!A:C,3,0),"") -> Sí
A11: CUARTAS GIL SEBASTIAN | B11: sebastian.cuartas1@udea.edu.co | C11: =IFERROR(ROUND(AVERAGE(E11:I11),1),"") -> 2.8 | D11: =VLOOKUP(B11,consolidado_notas!B:E,4,0) -> 7 | E11: 5 | F11: 0 | G11: 0 | H11: =IFERROR(VLOOKUP(D11&H$2&"Total",retroalimenación!D:F,3,0),"") -> 4.5 | I11: =H11 -> 4.5 | J11: =IFERROR(VLOOKUP(B11,seguimientos_extra!A:C,3,0),"")
A12: ALVAREZ FERNANDEZ ALANIS | B12: alanis.alvarez@udea.edu.co | C12: =IFERROR(ROUND(AVERAGE(E12:I12),1),"") -> 4.9 | D12: =VLOOKUP(B12,consolidado_notas!B:E,4,0) -> 1 | E12: 5 | F12: 5 | G12: 5 | H12: =IFERROR(VLOOKUP(D12&H$2&"Total",retroalimenación!D:F,3,0),"") -> 4.8 | I12: =H12 -> 4.8 | J12: =IFERROR(VLOOKUP(B12,seguimientos_extra!A:C,3,0),"")
A13: AMAYA LEÓN ALEXÁNDER | B13: alexander.amaya@udea.edu.co | C13: =IFERROR(ROUND(AVERAGE(E13:I13),1),"") -> 4 | D13: =VLOOKUP(B13,consolidado_notas!B:E,4,0) -> 2 | E13: 0 | F13: 5 | G13: 5 | H13: =IFERROR(VLOOKUP(D13&H$2&"Total",retroalimenación!D:F,3,0),"") -> 5 | I13: =H13 -> 5 | J13: =IFERROR(VLOOKUP(B13,seguimientos_extra!A:C,3,0),"")
A14: BETANCOURT FUENTES LAURA CAMILA | B14: laura.betancourt1@udea.edu.co | C14: =IFERROR(ROUND(AVERAGE(E14:I14),1),"") -> 3.7 | D14: =VLOOKUP(B14,consolidado_notas!B:E,4,0) -> 3 | E14: 5 | F14: 0 | G14: 5 | H14: =IFERROR(VLOOKUP(D14&H$2&"Total",retroalimenación!D:F,3,0),"") -> 4.2 | I14: =H14 -> 4.2 | J14: =IFERROR(VLOOKUP(B14,seguimientos_extra!A:C,3,0),"")
A15: BLANDÓN RAMÍREZ MANUELA | B15: manuela.blandon@udea.edu.co | C15: =IFERROR(ROUND(AVERAGE(E15:I15),1),"") -> 5 | D15: =VLOOKUP(B15,consolidado_notas!B:E,4,0) -> 2 | E15: 5 | F15: 5 | G15: 5 | H15: =IFERROR(VLOOKUP(D15&H$2&"Total",retroalimenación!D:F,3,0),"") -> 5 | I15: =H15 -> 5 | J15: =IFERROR(VLOOKUP(B15,seguimientos_extra!A:C,3,0),"")
A16: CAICEDO AGUIRRE MATEO | B16: mateo.caicedo@udea.edu.co | C16: =IFERROR(ROUND(AVERAGE(E16:I16),1),"") -> 3.8 | D16: =VLOOKUP(B16,consolidado_notas!B:E,4,0) -> 8 | E16: 0 | F16: 5 | G16: 5 | H16: =IFERROR(VLOOKUP(D16&H$2&"Total",retroalimenación!D:F,3,0),"") -> 4.4 | I16: =H16 -> 4.4 | J16: =IFERROR(VLOOKUP(B16,seguimientos_extra!A:C,3,0),"")
A17: CARDONA MOLINA JUAN ESTEBAN | B17: esteban.cardona6@udea.edu.co | C17: =IFERROR(ROUND(AVERAGE(E17:I17),1),"") -> 4.9 | D17: =VLOOKUP(B17,consolidado_notas!B:E,4,0) -> 1 | E17: 5 | F17: 5 | G17: 5 | H17: =IFERROR(VLOOKUP(D17&H$2&"Total",retroalimenación!D:F,3,0),"") -> 4.8 | I17: =H17 -> 4.8 | J17: =IFERROR(VLOOKUP(B17,seguimientos_extra!A:C,3,0),"")
A18: GUZMAN ZORRILLA NATALIA XIMENA | B18: natalia.guzmanz@udea.edu.co | C18: =IFERROR(ROUND(AVERAGE(E18:I18),1),"") -> 4.8 | D18: =VLOOKUP(B18,consolidado_notas!B:E,4,0) -> 7 | E18: 5 | F18: 5 | G18: 5 | H18: =IFERROR(VLOOKUP(D18&H$2&"Total",retroalimenación!D:F,3,0),"") -> 4.5 | I18: =H18 -> 4.5 | J18: =IFERROR(VLOOKUP(B18,seguimientos_extra!A:C,3,0),"")
A19: MARIN ZULUAGA SIMON | B19: simon.marinz@udea.edu.co | C19: =IFERROR(ROUND(AVERAGE(E19:I19),1),"") -> 3.8 | D19: =VLOOKUP(B19,consolidado_notas!B:E,4,0) -> 7 | E19: 0 | F19: 5 | G19: 5 | H19: =IFERROR(VLOOKUP(D19&H$2&"Total",retroalimenación!D:F,3,0),"") -> 4.5 | I19: =H19 -> 4.5 | J19: =IFERROR(VLOOKUP(B19,seguimientos_extra!A:C,3,0),"")
A20: MOLINA AMAYA AURA MARÍA | B20: aura.molina@udea.edu.co | C20: =IFERROR(ROUND(AVERAGE(E20:I20),1),"") -> 4.7 | D20: =VLOOKUP(B20,consolidado_notas!B:E,4,0) -> 3 | E20: 5 | F20: 5 | G20: 5 | H20: =IFERROR(VLOOKUP(D20&H$2&"Total",retroalimenación!D:F,3,0),"") -> 4.2 | I20: =H20 -> 4.2 | J20: =IFERROR(VLOOKUP(B20,seguimientos_extra!A:C,3,0),"")
A21: MOLINA OCAMPO JUAN JOSE | B21: juanj.molina1@udea.edu.co | C21: =IFERROR(ROUND(AVERAGE(E21:I21),1),"") -> 4.8 | D21: =VLOOKUP(B21,consolidado_notas!B:E,4,0) -> 4 | E21: 5 | F21: 5 | G21: 5 | H21: =IFERROR(VLOOKUP(D21&H$2&"Total",retroalimenación!D:F,3,0),"") -> 4.4 | I21: =H21 -> 4.4 | J21: =IFERROR(VLOOKUP(B21,seguimientos_extra!A:C,3,0),"")
A22: PEREZ CASTILLA KAREN MARCELA | B22: karen.perezc@udea.edu.co | C22: =IFERROR(ROUND(AVERAGE(E22:I22),1),"") -> 5 | D22: =VLOOKUP(B22,consolidado_notas!B:E,4,0) -> 2 | E22: 5 | F22: 5 | G22: 5 | H22: =IFERROR(VLOOKUP(D22&H$2&"Total",retroalimenación!D:F,3,0),"") -> 5 | I22: =H22 -> 5 | J22: =IFERROR(VLOOKUP(B22,seguimientos_extra!A:C,3,0),"")
... A27: SOTO TABORDA JUAN ESTEBAN | B27: esteban.soto1@udea.edu.co | C27: =IFERROR(ROUND(AVERAGE(E27:I27),1),"") -> 3.9 | D27: =VLOOKUP(B27,consolidado_notas!B:E,4,0) -> 1 | E27: 5 | F27: 5 | G27: 0 | H27: =IFERROR(VLOOKUP(D27&H$2&"Total",retroalimenación!D:F,3,0),"") -> 4.8 | I27: =H27 -> 4.8 | J27: =IFERROR(VLOOKUP(B27,seguimientos_extra!A:C,3,0),"")

Sheet seguimiento_finanzas
A2: Nombre | B2: Correo | C2: Total seguimiento con bonificación | D2: Grupo 4 | E2: 1. Claves que impactarán finanzas | F2: 2. Artículo aplicaciónes en salud | G2: 3. Avances finanzas en clase 1 | H2: 4. Avances finanzas en clase 2 | I2: 5. Avances finanzas en clase 3 | J2: Seguimientos
A3: OSORIO LÓPEZ JUAN FELIPE | B3: jfelipe.osorio@udea.edu.co | C3: =IFERROR(ROUND(AVERAGE(E3:I3),1),"") -> 4.9 | D3: =IFERROR(VLOOKUP(B3,consolidado_notas!B:E,4,0),"") -> 4 | E3: =VLOOKUP(B3,seguimientos_extra!A:B,2,0) -> 5 | F3: =E3 -> 5 | G3: =IFERROR(VLOOKUP(D3&$G$2&"Total",retroalimenación!D:F,3,0),"") -> 4.5 | H3: =IFERROR(VLOOKUP(D3&$H$2&"Total",retroalimenación!D:F,3,0),"") -> 5 | I3: =IFERROR(VLOOKUP(D3&$I$2&"Total",retroalimenación!D:F,3,0),"") -> 5 | J3: =IFERROR(VLOOKUP(B3,seguimientos_extra!A:C,3,0),"") -> Sí
A4: CONTRERAS TRILLOS OSIRIS | B4: osiris.contreras@udea.edu.co | C4: =IFERROR(ROUND(AVERAGE(E4:H4),1),"") -> 4.6 | D4: =IFERROR(VLOOKUP(B4,consolidado_notas!B:E,4,0),"") -> 4 | E4: =VLOOKUP(B4,seguimientos_extra!A:B,2,0) -> 4.5 | F4: =E4 -> 4.5 | G4: =IFERROR(VLOOKUP(D4&$G$2&"Total",retroalimenación!D:F,3,0),"") -> 4.5 | H4: =IFERROR(VLOOKUP(D4&$H$2&"Total",retroalimenación!D:F,3,0),"") -> 5 | I4: =IFERROR(VLOOKUP(D4&$I$2&"Total",retroalimenación!D:F,3,0),"") -> 5 | J4: =IFERROR(VLOOKUP(B4,seguimientos_extra!A:C,3,0),"") -> Sí
A5: ÁLVAREZ LÓPEZ ALEJANDRO | B5: alejandro.alvarezl@udea.edu.co | C5: =IFERROR(ROUND(AVERAGE(E5:H5),1),"") -> 3.6 | D5: =IFERROR(VLOOKUP(B5,consolidado_notas!B:E,4,0),"") -> 5 | E5: =VLOOKUP(B5,seguimientos_extra!A:B,2,0) -> 4.7 | F5: =E5 -> 4.7 | G5: =IFERROR(VLOOKUP(D5&$G$2&"Total",retroalimenación!D:F,3,0),"") -> 5 | H5: =IFERROR(VLOOKUP(D5&$H$2&"Total",retroalimenación!D:F,3,0),"") -> 0 | I5: =IFERROR(VLOOKUP(D5&$I$2&"Total",retroalimenación!D:F,3,0),"") -> 4.5 | J5: =IFERROR(VLOOKUP(B5,seguimientos_extra!A:C,3,0),"") -> Sí
A6: ARROYAVE MURILLO JUAN DIEGO | B6: juan.arroyave14@udea.edu.co | C6: =IFERROR(ROUND(AVERAGE(E6:H6),1),"") -> 3.7 | D6: =IFERROR(VLOOKUP(B6,consolidado_notas!B:E,4,0),"") -> 5 | E6: =VLOOKUP(B6,seguimientos_extra!A:B,2,0) -> 4.8 | F6: =E6 -> 4.8 | G6: =IFERROR(VLOOKUP(D6&$G$2&"Total",retroalimenación!D:F,3,0),"") -> 5 | H6: =IFERROR(VLOOKUP(D6&$H$2&"Total",retroalimenación!D:F,3,0),"") -> 0 | I6: =IFERROR(VLOOKUP(D6&$I$2&"Total",retroalimenación!D:F,3,0),"") -> 4.5 | J6: =IFERROR(VLOOKUP(B6,seguimientos_extra!A:C,3,0),"") -> Sí
A7: DUSSAN PUERTA ESTEFANIA | B7: estefania.dussan@udea.edu.co | C7: =IFERROR(ROUND(AVERAGE(E7:H7),1),"") -> 3.8 | D7: =IFERROR(VLOOKUP(B7,consolidado_notas!B:E,4,0),"") -> 5 | E7: =VLOOKUP(B7,seguimientos_extra!A:B,2,0) -> 5 | F7: =E7 -> 5 | G7: =IFERROR(VLOOKUP(D7&$G$2&"Total",retroalimenación!D:F,3,0),"") -> 5 | H7: =IFERROR(VLOOKUP(D7&$H$2&"Total",retroalimenación!D:F,3,0),"") -> 0 | I7: =IFERROR(VLOOKUP(D7&$I$2&"Total",retroalimenación!D:F,3,0),"") -> 4.5 | J7: =IFERROR(VLOOKUP(B7,seguimientos_extra!A:C,3,0),"") -> Sí
A8: SÁNCHEZ ÁLVAREZ SEBASTIÁN | B8: sebastian.sanchez9@udea.edu.co | C8: =IFERROR(ROUND(AVERAGE(E8:H8),1),"") -> 3.7 | D8: =IFERROR(VLOOKUP(B8,consolidado_notas!B:E,4,0),"") -> 5 | E8: =VLOOKUP(B8,seguimientos_extra!A:B,2,0) -> 4.8 | F8: =E8 -> 4.8 | G8: =IFERROR(VLOOKUP(D8&$G$2&"Total",retroalimenación!D:F,3,0),"") -> 5 | H8: =IFERROR(VLOOKUP(D8&$H$2&"Total",retroalimenación!D:F,3,0),"") -> 0 | I8: =IFERROR(VLOOKUP(D8&$I$2&"Total",retroalimenación!D:F,3,0),"") -> 4.5 | J8: =IFERROR(VLOOKUP(B8,seguimientos_extra!A:C,3,0),"") -> Sí
A9: ARABIA ÁLVAREZ PAOLA ANDREA | B9: paola.arabia@udea.edu.co | C9: =IFERROR(ROUND(AVERAGE(E9:H9),1),"") -> 2.3 | D9: =IFERROR(VLOOKUP(B9,consolidado_notas!B:E,4,0),"") -> 8 | E9: =VLOOKUP(B9,seguimientos_extra!A:B,2,0) -> 4.5 | F9: =E9 -> 4.5 | G9: =IFERROR(VLOOKUP(D9&$G$2&"Total",retroalimenación!D:F,3,0),"") -> 0 | H9: =IFERROR(VLOOKUP(D9&$H$2&"Total",retroalimenación!D:F,3,0),"") -> 0 | I9: =IFERROR(VLOOKUP(D9&$I$2&"Total",retroalimenación!D:F,3,0),"") -> 3 | J9: =IFERROR(VLOOKUP(B9,seguimientos_extra!A:C,3,0),"") -> Sí
A10: GUERRERO LOBO LEIDYS | B10: leidys.guerrero@udea.edu.co | C10: =IFERROR(ROUND(AVERAGE(E10:H10),1),"") -> 2.2 | D10: =IFERROR(VLOOKUP(B10,consolidado_notas!B:E,4,0),"") -> 8 | E10: =VLOOKUP(B10,seguimientos_extra!A:B,2,0) -> 4.4 | F10: =E10 -> 4.4 | G10: =IFERROR(VLOOKUP(D10&$G$2&"Total",retroalimenación!D:F,3,0),"") -> 0 | H10: =IFERROR(VLOOKUP(D10&$H$2&"Total",retroalimenación!D:F,3,0),"") -> 0 | I10: =IFERROR(VLOOKUP(D10&$I$2&"Total",retroalimenación!D:F,3,0),"") -> 3 | J10: =IFERROR(VLOOKUP(B10,seguimientos_extra!A:C,3,0),"") -> Sí
A11: CARDONA MOLINA JUAN ESTEBAN | B11: esteban.cardona6@udea.edu.co | C11: =IFERROR(ROUND(AVERAGE(E11:H11),1),"") -> 4.9 | D11: =IFERROR(VLOOKUP(B11,consolidado_notas!B:E,4,0),"") -> 1 | E11: 5 | F11: 4.5 | G11: =IFERROR(VLOOKUP(D11&$G$2&"Total",retroalimenación!D:F,3,0),"") -> 5 | H11: =IFERROR(VLOOKUP(D11&$H$2&"Total",retroalimenación!D:F,3,0),"") -> 5 | I11: =IFERROR(VLOOKUP(D11&$I$2&"Total",retroalimenación!D:F,3,0),"") -> 5 | J11: =IFERROR(VLOOKUP(B11,seguimientos_extra!A:C,3,0),"")
A12: ALVAREZ FERNANDEZ ALANIS | B12: alanis.alvarez@udea.edu.co | C12: =IFERROR(ROUND(AVERAGE(E12:H12),1),"") -> 4.9 | D12: =IFERROR(VLOOKUP(B12,consolidado_notas!B:E,4,0),"") -> 1 | E12: 5 | F12: 4.7 | G12: =IFERROR(VLOOKUP(D12&$G$2&"Total",retroalimenación!D:F,3,0),"") -> 5 | H12: =IFERROR(VLOOKUP(D12&$H$2&"Total",retroalimenación!D:F,3,0),"") -> 5 | I12: =IFERROR(VLOOKUP(D12&$I$2&"Total",retroalimenación!D:F,3,0),"") -> 5 | J12: =IFERROR(VLOOKUP(B12,seguimientos_extra!A:C,3,0),"")
A13: RESTREPO OLARTE SANTIAGO | B13: santiago.restrepo23@udea.edu.co | C13: =IFERROR(ROUND(AVERAGE(E13:H13),1),"") -> 4.9 | D13: =IFERROR(VLOOKUP(B13,consolidado_notas!B:E,4,0),"") -> 1 | E13: 4.7 | F13: 4.7 | G13: =IFERROR(VLOOKUP(D13&$G$2&"Total",retroalimenación!D:F,3,0),"") -> 5 | H13: =IFERROR(VLOOKUP(D13&$H$2&"Total",retroalimenación!D:F,3,0),"") -> 5 | I13: =IFERROR(VLOOKUP(D13&$I$2&"Total",retroalimenación!D:F,3,0),"") -> 5 | J13: =IFERROR(VLOOKUP(B13,seguimientos_extra!A:C,3,0),"")
A14: SOTO TABORDA JUAN ESTEBAN | B14: esteban.soto1@udea.edu.co | C14: =IFERROR(ROUND(AVERAGE(E14:H14),1),"") -> 3.7 | D14: =IFERROR(VLOOKUP(B14,consolidado_notas!B:E,4,0),"") -> 1 | E14: 4.7 | F14: 0 | G14: =IFERROR(VLOOKUP(D14&$G$2&"Total",retroalimenación!D:F,3,0),"") -> 5 | H14: =IFERROR(VLOOKUP(D14&$H$2&"Total",retroalimenación!D:F,3,0),"") -> 5 | I14: =IFERROR(VLOOKUP(D14&$I$2&"Total",retroalimenación!D:F,3,0),"") -> 5 | J14: =IFERROR(VLOOKUP(B14,seguimientos_extra!A:C,3,0),"")
A15: DEL VALLE CORREA DAYANA SOFIA | B15: dayana.delvalle@udea.edu.co | C15: =IFERROR(ROUND(AVERAGE(E15:H15),1),"") -> 4.8 | D15: =IFERROR(VLOOKUP(B15,consolidado_notas!B:E,4,0),"") -> 2 | E15: 4.5 | F15: 4.5 | G15: =IFERROR(VLOOKUP(D15&$G$2&"Total",retroalimenación!D:F,3,0),"") -> 5 | H15: =IFERROR(VLOOKUP(D15&$H$2&"Total",retroalimenación!D:F,3,0),"") -> 5 | I15: =IFERROR(VLOOKUP(D15&$I$2&"Total",retroalimenación!D:F,3,0),"") -> 5 | J15: =IFERROR(VLOOKUP(B15,seguimientos_extra!A:C,3,0),"")
A16: AMAYA LEÓN ALEXÁNDER | B16: alexander.amaya@udea.edu.co | C16: =IFERROR(ROUND(AVERAGE(E16:H16),1),"") -> 4.9 | D16: =IFERROR(VLOOKUP(B16,consolidado_notas!B:E,4,0),"") -> 2 | E16: 5 | F16: 4.7 | G16: =IFERROR(VLOOKUP(D16&$G$2&"Total",retroalimenación!D:F,3,0),"") -> 5 | H16: =IFERROR(VLOOKUP(D16&$H$2&"Total",retroalimenación!D:F,3,0),"") -> 5 | I16: =IFERROR(VLOOKUP(D16&$I$2&"Total",retroalimenación!D:F,3,0),"") -> 5 | J16: =IFERROR(VLOOKUP(B16,seguimientos_extra!A:C,3,0),"")
A17: BLANDÓN RAMÍREZ MANUELA | B17: manuela.blandon@udea.edu.co | C17: =IFERROR(ROUND(AVERAGE(E17:H17),1),"") -> 5 | D17: =IFERROR(VLOOKUP(B17,consolidado_notas!B:E,4,0),"") -> 2 | E17: 5 | F17: 5 | G17: =IFERROR(VLOOKUP(D17&$G$2&"Total",retroalimenación!D:F,3,0),"") -> 5 | H17: =IFERROR(VLOOKUP(D17&$H$2&"Total",retroalimenación!D:F,3,0),"") -> 5 | I17: =IFERROR(VLOOKUP(D17&$I$2&"Total",retroalimenación!D:F,3,0),"") -> 5 | J17: =IFERROR(VLOOKUP(B17,seguimientos_extra!A:C,3,0),"")
A18: PEREZ CASTILLA KAREN MARCELA | B18: karen.perezc@udea.edu.co | C18: =IFERROR(ROUND(AVERAGE(E18:H18),1),"") -> 5 | D18: =IFERROR(VLOOKUP(B18,consolidado_notas!B:E,4,0),"") -> 2 | E18: 5 | F18: 5 | G18: =IFERROR(VLOOKUP(D18&$G$2&"Total",retroalimenación!D:F,3,0),"") -> 5 | H18: =IFERROR(VLOOKUP(D18&$H$2&"Total",retroalimenación!D:F,3,0),"") -> 5 | I18: =IFERROR(VLOOKUP(D18&$I$2&"Total",retroalimenación!D:F,3,0),"") -> 5 | J18: =IFERROR(VLOOKUP(B18,seguimientos_extra!A:C,3,0),"")
A19: BETANCOURT FUENTES LAURA CAMILA | B19: laura.betancourt1@udea.edu.co | C19: =IFERROR(ROUND(AVERAGE(E19:H19),1),"") -> 4.3 | D19: =IFERROR(VLOOKUP(B19,consolidado_notas!B:E,4,0),"") -> 3 | E19: 4.7 | F19: 5 | G19: =IFERROR(VLOOKUP(D19&$G$2&"Total",retroalimenación!D:F,3,0),"") -> 4.5 | H19: =IFERROR(VLOOKUP(D19&$H$2&"Total",retroalimenación!D:F,3,0),"") -> 3 | I19: =IFERROR(VLOOKUP(D19&$I$2&"Total",retroalimenación!D:F,3,0),"") -> 4 | J19: =IFERROR(VLOOKUP(B19,seguimientos_extra!A:C,3,0),"")
A20: GIL PACHECO GILBERTO JOSÉ | B20: gilberto.gil1@udea.edu.co | C20: =IFERROR(ROUND(AVERAGE(E20:H20),1),"") -> 1.9 | D20: =IFERROR(VLOOKUP(B20,consolidado_notas!B:E,4,0),"") -> 3 | E20: 0 | F20: 0 | G20: =IFERROR(VLOOKUP(D20&$G$2&"Total",retroalimenación!D:F,3,0),"") -> 4.5 | H20: =IFERROR(VLOOKUP(D20&$H$2&"Total",retroalimenación!D:F,3,0),"") -> 3 | I20: =IFERROR(VLOOKUP(D20&$I$2&"Total",retroalimenación!D:F,3,0),"") -> 4 | J20: =IFERROR(VLOOKUP(B20,seguimientos_extra!A:C,3,0),"")
A21: MOLINA AMAYA AURA MARÍA | B21: aura.molina@udea.edu.co | C21: =IFERROR(ROUND(AVERAGE(E21:H21),1),"") -> 1.9 | D21: =IFERROR(VLOOKUP(B21,consolidado_notas!B:E,4,0),"") -> 3 | E21: 0 | F21: 0 | G21: =IFERROR(VLOOKUP(D21&$G$2&"Total",retroalimenación!D:F,3,0),"") -> 4.5 | H21: =IFERROR(VLOOKUP(D21&$H$2&"Total",retroalimenación!D:F,3,0),"") -> 3 | I21: =IFERROR(VLOOKUP(D21&$I$2&"Total",retroalimenación!D:F,3,0),"") -> 4 | J21: =IFERROR(VLOOKUP(B21,seguimientos_extra!A:C,3,0),"")
A22: MOLINA OCAMPO JUAN JOSE | B22: juanj.molina1@udea.edu.co | C22: =IFERROR(ROUND(AVERAGE(E22:H22),1),"") -> 2.4 | D22: =IFERROR(VLOOKUP(B22,consolidado_notas!B:E,4,0),"") -> 4 | E22: 0 | F22: 0 | G22: =IFERROR(VLOOKUP(D22&$G$2&"Total",retroalimenación!D:F,3,0),"") -> 4.5 | H22: =IFERROR(VLOOKUP(D22&$H$2&"Total",retroalimenación!D:F,3,0),"") -> 5 | I22: =IFERROR(VLOOKUP(D22&$I$2&"Total",retroalimenación!D:F,3,0),"") -> 5 | J22: =IFERROR(VLOOKUP(B22,seguimientos_extra!A:C,3,0),"")
... A27: CAICEDO AGUIRRE MATEO | B27: mateo.caicedo@udea.edu.co | C27: =IFERROR(ROUND(AVERAGE(E27:H27),1),"") -> 0 | D27: =IFERROR(VLOOKUP(B27,consolidado_notas!B:E,4,0),"") -> 8 | E27: 0 | F27: 0 | G27: =IFERROR(VLOOKUP(D27&$G$2&"Total",retroalimenación!D:F,3,0),"") -> 0 | H27: =IFERROR(VLOOKUP(D27&$H$2&"Total",retroalimenación!D:F,3,0),"") -> 0 | I27: =IFERROR(VLOOKUP(D27&$I$2&"Total",retroalimenación!D:F,3,0),"") -> 3 | J27: =IFERROR(VLOOKUP(B27,seguimientos_extra!A:C,3,0),"")

Sheet bonificaciones
A2: Nombre | B2: Correo | C2: Total bonificaciones | D2: A1: Artículo HR | E2: A2: particiapación inicio módulo salud | F2: A3: Opinión Artículo Salud | G2: A4: Claves Finanzas | H2: A6: Artículo salud | I2: A7: Participación en clse | J2: A8:
A3: ALVAREZ FERNANDEZ ALANIS | B3: alanis.alvarez@udea.edu.co | C3: =SUM(D3:R3) -> 0.4 | F3: 0.2 | G3: 0.2
A4: ÁLVAREZ LÓPEZ ALEJANDRO | B4: alejandro.alvarezl@udea.edu.co | C4: =SUM(D4:R4) -> 0
A5: AMAYA LEÓN ALEXÁNDER | B5: alexander.amaya@udea.edu.co | C5: =SUM(D5:R5) -> 0.6 | D5: 0.2 | F5: 0.2 | G5: 0.2
A6: ARABIA ÁLVAREZ PAOLA ANDREA | B6: paola.arabia@udea.edu.co | C6: =SUM(D6:R6) -> 0
A7: ARROYAVE MURILLO JUAN DIEGO | B7: juan.arroyave14@udea.edu.co | C7: =SUM(D7:R7) -> 0
A8: BETANCOURT FUENTES LAURA CAMILA | B8: laura.betancourt1@udea.edu.co | C8: =SUM(D8:R8) -> 0.4 | E8: 0.2 | H8: 0.2
A9: BLANDÓN RAMÍREZ MANUELA | B9: manuela.blandon@udea.edu.co | C9: =SUM(D9:R9) -> 0.6 | E9: 0.2 | F9: 0.2 | H9: 0.2
A10: CAICEDO AGUIRRE MATEO | B10: mateo.caicedo@udea.edu.co | C10: =SUM(D10:R10) -> 0
A11: CARDONA MOLINA JUAN ESTEBAN | B11: esteban.cardona6@udea.edu.co | C11: =SUM(D11:R11) -> 0.2 | F11: 0.2
A12: CONTRERAS TRILLOS OSIRIS | B12: osiris.contreras@udea.edu.co | C12: =SUM(D12:R12) -> 0.2 | D12: 0.2
A13: CUARTAS GIL SEBASTIAN | B13: sebastian.cuartas1@udea.edu.co | C13: =SUM(D13:R13) -> 0
A14: DEL VALLE CORREA DAYANA SOFIA | B14: dayana.delvalle@udea.edu.co | C14: =SUM(D14:R14) -> 0
A15: DUSSAN PUERTA ESTEFANIA | B15: estefania.dussan@udea.edu.co | C15: =SUM(D15:R15) -> 0
A16: GIL PACHECO GILBERTO JOSÉ | B16: gilberto.gil1@udea.edu.co | C16: =SUM(D16:R16) -> 0
A17: GUERRERO LOBO LEIDYS | B17: leidys.guerrero@udea.edu.co | C17: =SUM(D17:R17) -> 0
A18: GUZMAN ZORRILLA NATALIA XIMENA | B18: natalia.guzmanz@udea.edu.co | C18: =SUM(D18:R18) -> 0.4 | F18: 0.2 | G18: 0.2
A19: MARIN ZULUAGA SIMON | B19: simon.marinz@udea.edu.co | C19: =SUM(D19:R19) -> 0
A20: MOLINA AMAYA AURA MARÍA | B20: aura.molina@udea.edu.co | C20: =SUM(D20:R20) -> 0
A21: MOLINA OCAMPO JUAN JOSE | B21: juanj.molina1@udea.edu.co | C21: =SUM(D21:R21) -> 0
A22: OSORIO LÓPEZ JUAN FELIPE | B22: jfelipe.osorio@udea.edu.co | C22: =SUM(D22:R22) -> 1 | I22: 1
A23: PEREZ CASTILLA KAREN MARCELA | B23: karen.perezc@udea.edu.co | C23: =SUM(D23:R23) -> 0.4 | F23: 0.2 | H23: 0.2
A24: RESTREPO OLARTE SANTIAGO | B24: santiago.restrepo23@udea.edu.co | C24: =SUM(D24:R24) -> 0.6 | D24: 0.2 | E24: 0.2 | F24: 0.2
A25: SÁNCHEZ ÁLVAREZ SEBASTIÁN | B25: sebastian.sanchez9@udea.edu.co | C25: =SUM(D25:R25) -> 0
A26: SOTO TABORDA JUAN ESTEBAN | B26: esteban.soto1@udea.edu.co | C26: =SUM(D26:R26) -> 0.4 | D26: 0.2 | E26: 0.2
A27: TORO VILLEGAS JUAN JOSE | B27: juanj.toro@udea.edu.co | C27: =SUM(D27:R27) -> 0

Sheet retroalimenación
A1: Actividad | B1: Grupo | C1: Rubrica | D1: id | E1: Porcentaje | F1: Calificación | G1: Retroalimentación | H1: Observaciones presentación
A2: 4. Presentación de avances HR | B2: 1 | C2: Claridad | D2: =B2&A2&C2 -> 14. Presentación de avances HRClaridad | E2: 0.2 | F2: 4.5 | G2: Faltó presentar mejor en algunas partes y organizar mejor lo que iban a presentar y explicar la propuiesta de tablero y modelo para verificar
A3: 4. Presentación de avances HR | B3: 1 | C3: Avance | D3: =B3&A3&C3 -> 14. Presentación de avances HRAvance | E3: 0.2 | F3: 4.5 | G3: No era necesario exploratorio, faltó explicar mejor la selección de variables.
A4: 4. Presentación de avances HR | B4: 1 | C4: Comprensión | D4: =B4&A4&C4 -> 14. Presentación de avances HRComprensión | E4: 0.2 | F4: 3.7 | G4: Falta amplia mucho más el diseño de la solución, el diagrama de flujo no es necesario para el paso a paso y ocupa mucho espacio. Bien las métricas de negocio para medir es parte del diseño,
A5: 4. Presentación de avances HR | B5: 1 | C5: Innovación | D5: =B5&A5&C5 -> 14. Presentación de avances HRInnovación | E5: 0.2 | F5: 5 | G5: Métricas de negocio para medir impacto y tablero de power point
A6: 4. Presentación de avances HR | B6: 1 | C6: Errores | D6: =B6&A6&C6 -> 14. Presentación de avances HRErrores | E6: 0.2 | F6: 4.7 | G6: Cuidado con la eliminación de variables como género y performance rate, ante la duda si eliminarla manualmente o no, mejor no se elimina y que en la importancia de las variables se elimine en caso de que no pese.
A7: 4. Presentación de avances HR | B7: 1 | C7: Total | D7: =B7&A7&C7 -> 14. Presentación de avances HRTotal | E7: =SUM(E2:E6) -> 1 | F7: =SUMPRODUCT(E2:E6,F2:F6) -> 4.48
A8: 4. Presentación de avances HR | B8: =B2+1 -> 2 | C8: Claridad | D8: =B8&A8&C8 -> 24. Presentación de avances HRClaridad | E8: 0.2 | F8: 5
A9: 4. Presentación de avances HR | B9: =B3+1 -> 2 | C9: Avance | D9: =B9&A9&C9 -> 24. Presentación de avances HRAvance | E9: 0.2 | F9: 5
A10: 4. Presentación de avances HR | B10: =B4+1 -> 2 | C10: Comprensión | D10: =B10&A10&C10 -> 24. Presentación de avances HRComprensión | E10: 0.2 | F10: 5
A11: 4. Presentación de avances HR | B11: =B5+1 -> 2 | C11: Innovación | D11: =B11&A11&C11 -> 24. Presentación de avances HRInnovación | E11: 0.2 | F11: 4 | G11: Se puede utilizar más el diseño de la solución para usar creativamente los resultados del modelo, archivo de sql aparte por buena práctica
A12: 4. Presentación de avances HR | B12: =B6+1 -> 2 | C12: Errores | D12: =B12&A12&C12 -> 24. Presentación de avances HRErrores | E12: 0.2 | F12: 5
A13: 4. Presentación de avances HR | B13: =B7+1 -> 2 | C13: Total | D13: =B13&A13&C13 -> 24. Presentación de avances HRTotal | E13: =SUM(E8:E12) -> 1 | F13: =SUMPRODUCT(E8:E12,F8:F12) -> 4.8
A14: 4. Presentación de avances HR | B14: =B8+1 -> 3 | C14: Claridad | D14: =B14&A14&C14 -> 34. Presentación de avances HRClaridad | E14: 0.2 | F14: 3.5 | G14: Muy rapido la parte del código, hay que excoger qué se va a presentar y detenerse a explicar bien en esos puentos, falta mejorar la claridad en la exposicón
A15: 4. Presentación de avances HR | B15: =B9+1 -> 3 | C15: Avance | D15: =B15&A15&C15 -> 34. Presentación de avances HRAvance | E15: 0.2 | F15: 3.7 | G15: Todaía no habían entrenado modelos y ya deberían tnerse para comparar algoritmos
A16: 4. Presentación de avances HR | B16: =B10+1 -> 3 | C16: Comprensión | D16: =B16&A16&C16 -> 34. Presentación de avances HRComprensión | E16: 0.2 | F16: 5
A17: 4. Presentación de avances HR | B17: =B11+1 -> 3 | C17: Innovación | D17: =B17&A17&C17 -> 34. Presentación de avances HRInnovación | E17: 0.2 | F17: 5
A18: 4. Presentación de avances HR | B18: =B12+1 -> 3 | C18: Errores | D18: =B18&A18&C18 -> 34. Presentación de avances HRErrores | E18: 0.2 | F18: 3 | G18: Había varios errores como las fechas de train y test, justificar regresión logística por multiclase cuando no es su problema, usar variables retirment type para predecor
A19: 4. Presentación de avances HR | B19: =B13+1 -> 3 | C19: Total | D19: =B19&A19&C19 -> 34. Presentación de avances HRTotal | E19: =SUM(E14:E18) -> 1 | F19: =SUMPRODUCT(E14:E18,F14:F18) -> 4.04
A20: 4. Presentación de avances HR | B20: =B14+1 -> 4 | C20: Claridad | D20: =B20&A20&C20 -> 44. Presentación de avances HRClaridad | E20: 0.2 | F20: 4 | G20: Muy buena presentación, faltó explicar mejor la parte de selección de variables, estaba bien el código pero no fue clara la presentación. Fltó utilizar mejor el tiempo para presentar más detallados los temas que se necesitaban presentar
A21: 4. Presentación de avances HR | B21: =B15+1 -> 4 | C21: Avance | D21: =B21&A21&C21 -> 44. Presentación de avances HRAvance | E21: 0.2 | F21: 4.5 | G21: No era necesario presentar la exploración
A22: 4. Presentación de avances HR | B22: =B16+1 -> 4 | C22: Comprensión | D22: =B22&A22&C22 -> 44. Presentación de avances HRComprensión | E22: 0.2 | F22: 4.5 | G22: El diseño de la solución está bien planteado, pero se pueden dejar como un solo paso todo lo relacionado con entrenamiento, selección de variables, entrnado de modelos y predicción, eso puede ser uno solo y el resto de pasos sí son propios del diseño.
A23: 4. Presentación de avances HR | B23: =B17+1 -> 4 | C23: Innovación | D23: =B23&A23&C23 -> 44. Presentación de avances HRInnovación | E23: 0.2 | F23: 4.5
A24: 4. Presentación de avances HR | B24: =B18+1 -> 4 | C24: Errores | D24: =B24&A24&C24 -> 44. Presentación de avances HRErrores | E24: 0.2 | F24: 5
A25: 4. Presentación de avances HR | B25: =B19+1 -> 4 | C25: Total | D25: =B25&A25&C25 -> 44. Presentación de avances HRTotal | E25: =SUM(E20:E24) -> 1 | F25: =SUMPRODUCT(E20:E24,F20:F24) -> 4.5
A26: 4. Presentación de avances HR | B26: =B20+1 -> 5 | C26: Claridad | D26: =B26&A26&C26 -> 54. Presentación de avances HRClaridad | E26: 0.2 | F26: 3 | G26: Faltó coordinar mejor la presnetación, muy largo la presentación de diseño y muy corto en otros temas por falta de tiempo
A27: 4. Presentación de avances HR | B27: =B21+1 -> 5 | C27: Avance | D27: =B27&A27&C27 -> 54. Presentación de avances HRAvance | E27: 0.2 | F27: 4 | G27: Faltó presentación de variables seleccionadas por tiempo
A28: 4. Presentación de avances HR | B28: =B22+1 -> 5 | C28: Comprensión | D28: =B28&A28&C28 -> 54. Presentación de avances HRComprensión | E28: 0.2 | F28: 4.8 | G28: No es necesario paso a paso de design thinking, enfocarse en el diseño que está bien propuesto con la clasificación en categorías, hacer énfasis en esa parte, eso ya incluye diseño de negocio y técnico.
A29: 4. Presentación de avances HR | B29: =B23+1 -> 5 | C29: Innovación | D29: =B29&A29&C29 -> 54. Presentación de avances HRInnovación | E29: 0.2 | F29: 5 | G29: Bien la clasificación del modelo y uso de sql
A30: 4. Presentación de avances HR | B30: =B24+1 -> 5 | C30: Errores | D30: =B30&A30&C30 -> 54. Presentación de avances HRErrores | E30: 0.2 | F30: 5
A31: 4. Presentación de avances HR | B31: =B25+1 -> 5 | C31: Total | D31: =B31&A31&C31 -> 54. Presentación de avances HRTotal | E31: =SUM(E26:E30) -> 1 | F31: =SUMPRODUCT(E26:E30,F26:F30) -> 4.36
A32: 4. Presentación de avances HR | B32: =B26+1 -> 6 | C32: Claridad | D32: =B32&A32&C32 -> 64. Presentación de avances HRClaridad | E32: 0.2 | F32: 4.5 | G32: Muy buena presentación, muy bien preparada, faltó mejorar los saltos entre código y presentación ser más claro explicando código
A33: 4. Presentación de avances HR | B33: =B27+1 -> 6 | C33: Avance | D33: =B33&A33&C33 -> 64. Presentación de avances HRAvance | E33: 0.2 | F33: 3.7 | G33: Importante hacer el cruce de datos para que ya te quede estructura lista para modelo con recomendaciones que te di
A34: 4. Presentación de avances HR | B34: =B28+1 -> 6 | C34: Comprensión | D34: =B34&A34&C34 -> 64. Presentación de avances HRComprensión | E34: 0.2 | F34: 4.8 | G34: Implementación de la solución es diseño de la solución, decir cuántos empleados puedo trabajarr en cada categoría o presupuesto
A35: 4. Presentación de avances HR | B35: =B29+1 -> 6 | C35: Innovación | D35: =B35&A35&C35 -> 64. Presentación de avances HRInnovación | E35: 0.2 | F35: 5 | G35: Muy buenas ideas en diseño
A36: 4. Presentación de avances HR | B36: =B30+1 -> 6 | C36: Errores | D36: =B36&A36&C36 -> 64. Presentación de avances HRErrores | E36: 0.2 | F36: 3.7 | G36: cuidado con tratamiento de resignación con promedios y cruce de datos
A37: 4. Presentación de avances HR | B37: =B31+1 -> 6 | C37: Total | D37: =B37&A37&C37 -> 64. Presentación de avances HRTotal | E37: =SUM(E32:E36) -> 1 | F37: =SUMPRODUCT(E32:E36,F32:F36) -> 4.34
A38: 4. Presentación de avances HR | B38: =B32+1 -> 7 | C38: Claridad | D38: =B38&A38&C38 -> 74. Presentación de avances HRClaridad | E38: 0.2 | F38: 4 | G38: Se enredó explicando, no mostraron el cruce, muy ráaido por el código, preparar mejor qué temas presentar y explicarlos mejor
A39: 4. Presentación de avances HR | B39: =B33+1 -> 7 | C39: Avance | D39: =B39&A39&C39 -> 74. Presentación de avances HRAvance | E39: 0.2 | F39: 3.5 | G39: Faltó modelos
A40: 4. Presentación de avances HR | B40: =B34+1 -> 7 | C40: Comprensión | D40: =B40&A40&C40 -> 74. Presentación de avances HRComprensión | E40: 0.2 | F40: 4.7 | G40: Muy bien planteado el diseño pero hay que organizarlo
A41: 4. Presentación de avances HR | B41: =B35+1 -> 7 | C41: Innovación | D41: =B41&A41&C41 -> 74. Presentación de avances HRInnovación | E41: 0.2 | F41: 5 | G41: Muy bien la descripción del probelma
A42: 4. Presentación de avances HR | B42: =B36+1 -> 7 | C42: Errores | D42: =B42&A42&C42 -> 74. Presentación de avances HRErrores | E42: 0.2 | F42: 3.5 | G42: Errores al no eliminar 2015, en diseño de la solución pusieron variables imporantes dos veces, falta organizar el diseño
A43: 4. Presentación de avances HR | B43: =B37+1 -> 7 | C43: Total | D43: =B43&A43&C43 -> 74. Presentación de avances HRTotal | E43: =SUM(E38:E42) -> 1 | F43: =SUMPRODUCT(E38:E42,F38:F42) -> 4.14
A44: 4. Presentación de avances HR | B44: =B38+1 -> 8 | C44: Claridad | D44: =B44&A44&C44 -> 84. Presentación de avances HRClaridad | E44: 0.2 | F44: 3 | G44: Llegaron tarde después de tiempo hay que organizarse bien para la próxima presentación que es avisada con anticipación. Faltó mucha claridad en la presentación, por ejemplo mostraron unas matriz de confusión sin explicar bien de qué eran de qué tipo de modelo y contaron y mostraron código muy rápido sin mostrar que se estaba haciendo
A45: 4. Presentación de avances HR | B45: =B39+1 -> 8 | C45: Avance | D45: =B45&A45&C45 -> 84. Presentación de avances HRAvance | E45: 0.2 | F45: 3.5 | G45: En los avances debería estar selección de variables y comparación de modelos y no estaba, lo que se presentó fue análisis de modelo que es un punto posterior, tener en cuenta los temas de la guía que se deben presentar
A46: 4. Presentación de avances HR | B46: =B40+1 -> 8 | C46: Comprensión | D46: =B46&A46&C46 -> 84. Presentación de avances HRComprensión | E46: 0.2 | F46: 4 | G46: Falta detalles técnicos en diseño de la solución, explicar el problema que están resolviendo
A47: 4. Presentación de avances HR | B47: =B41+1 -> 8 | C47: Innovación | D47: =B47&A47&C47 -> 84. Presentación de avances HRInnovación | E47: 0.2 | F47: 3 | G47: Hay que proponer cosas creativas en diseño de la solución
A48: 4. Presentación de avances HR | B48: =B42+1 -> 8 | C48: Errores | D48: =B48&A48&C48 -> 84. Presentación de avances HRErrores | E48: 0.2 | F48: 4 | G48: El uso de las gráficos no es el más apropiado
A49: 4. Presentación de avances HR | B49: =B43+1 -> 8 | C49: Total | D49: =B49&A49&C49 -> 84. Presentación de avances HRTotal | E49: =SUM(E44:E48) -> 1 | F49: =SUMPRODUCT(E44:E48,F44:F48) -> 3.5
A50: Trabajo HR | B50: 1 | C50: Creatividad | D50: =B50&A50&C50 -> 1Trabajo HRCreatividad | E50: 0.1 | F50: 5
A51: Trabajo HR | B51: 1 | C51: Pertinencia | D51: =B51&A51&C51 -> 1Trabajo HRPertinencia | E51: 0.05 | F51: 5
A52: Trabajo HR | B52: 1 | C52: código | D52: =B52&A52&C52 -> 1Trabajo HRcódigo | E52: 0.3 | F52: 5
A53: Trabajo HR | B53: 1 | C53: Análisis | D53: =B53&A53&C53 -> 1Trabajo HRAnálisis | E53: 0.35 | F53: 5
A54: Trabajo HR | B54: 1 | C54: Redacción | D54: =B54&A54&C54 -> 1Trabajo HRRedacción | E54: 0.2 | F54: 5
A55: Trabajo HR | B55: =B54 -> 1 | C55: Total | D55: =B55&A55&C55 -> 1Trabajo HRTotal | E55: =SUM(E50:E54) -> 1 | F55: =SUMPRODUCT(E50:E54,F50:F54) -> 5 | G55: Excelente trabajo, muy organizado. La unica recomendación es que la optimización de hiperparámetro en el informe la pusieron antes de la selecición de modelo, la recomendación es que seleccionen el modelo y al seleccionado le afinen hiperparámetros
A56: Trabajo HR | B56: =B50+1 -> 2 | C56: Creatividad | D56: =B56&A56&C56 -> 2Trabajo HRCreatividad | E56: 0.1 | F56: 5
A57: Trabajo HR | B57: =B51+1 -> 2 | C57: Pertinencia | D57: =B57&A57&C57 -> 2Trabajo HRPertinencia | E57: 0.05 | F57: 5
A58: Trabajo HR | B58: =B52+1 -> 2 | C58: código | D58: =B58&A58&C58 -> 2Trabajo HRcódigo | E58: 0.3 | F58: 5
A59: Trabajo HR | B59: =B53+1 -> 2 | C59: Análisis | D59: =B59&A59&C59 -> 2Trabajo HRAnálisis | E59: 0.35 | F59: 5
A60: Trabajo HR | B60: =B54+1 -> 2 | C60: Redacción | D60: =B60&A60&C60 -> 2Trabajo HRRedacción | E60: 0.2 | F60: 5
A61: Trabajo HR | B61: =B55+1 -> 2 | C61: Total | D61: =B61&A61&C61 -> 2Trabajo HRTotal | E61: =SUM(E56:E60) -> 1 | F61: 5 | G61: Muy buen trabajo, muy buenas las propuestas de analizar por tipo de cargo para plantear las estrategias y muy organizado el código
A62: Trabajo HR | B62: =B56+1 -> 3 | C62: Creatividad | D62: =B62&A62&C62 -> 3Trabajo HRCreatividad | E62: 0.1 | F62: 4 | G62: Muy buena idea en el diseño de dividir en niveles de criticidad pero no lo hicieron en el despliegue, solo quedo en el diseño
A63: Trabajo HR | B63: =B57+1 -> 3 | C63: Pertinencia | D63: =B63&A63&C63 -> 3Trabajo HRPertinencia | E63: 0.05 | F63: 4 | G63: En el diseño de la solución no es necesario poner, exploración y procesamiento, selección de variables entrenamiento, se puede poner una sola caja para hacer enfásis en el procesos de negocio no la construcción del modelo. El resto están bien
A64: Trabajo HR | B64: =B58+1 -> 3 | C64: código | D64: =B64&A64&C64 -> 3Trabajo HRcódigo | E64: 0.3 | F64: 4.7 | G64: Faltó elliminar el pycache con el gitignore el main.swp y poner datadiictionary en carpéta de datos para que quede más organziado
A65: Trabajo HR | B65: =B59+1 -> 3 | C65: Análisis | D65: =B65&A65&C65 -> 3Trabajo HRAnálisis | E65: 0.35 | F65: 4.5 | G65: Faltó explicar por qué escogieron F1 score, muy buen análisis de falsos postiivos y falsos negativos, muy buen analísis de las variables importantes y propuestas.
A66: Trabajo HR | B66: =B60+1 -> 3 | C66: Redacción | D66: =B66&A66&C66 -> 3Trabajo HRRedacción | E66: 0.2 | F66: 4.5 | G66: Selección de algoritmos está repetido en 6 y 7, el pantallazo al lado de la matriz de confusión no se ve bien, se debió pasar a una taba.
A67: Trabajo HR | B67: =B61+1 -> 3 | C67: Total | D67: =B67&A67&C67 -> 3Trabajo HRTotal | E67: =SUM(E62:E66) -> 1 | F67: =SUMPRODUCT(E62:E66,F62:F66) -> 4.485
A68: Trabajo HR | B68: =B62+1 -> 4 | C68: Creatividad | D68: =B68&A68&C68 -> 4Trabajo HRCreatividad | E68: 0.1 | F68: 4.7 | G68: Faltó más desarrollar las propuestas como la clasificación de empleados para validar la creatividad de la propuesta. Muy bien la propuesta de kmeans para explorar
A69: Trabajo HR | B69: =B63+1 -> 4 | C69: Pertinencia | D69: =B69&A69&C69 -> 4Trabajo HRPertinencia | E69: 0.05 | F69: 4 | G69: No es necesario poner selección de variables, limpieza y transformación y tareas para entrenar un modelo, se pone entrenar modelo y eso incluye todas las tareas, de esta manera el énfasis está en el proceso de negocio no en los pasos para construir el modelo. En el diseño de la solución gráfico, se pone clasificar empleados pero no se describe cómo, en las descripciones solo hablan de encontrar variables importantes.
A70: Trabajo HR | B70: =B64+1 -> 4 | C70: código | D70: =B70&A70&C70 -> 4Trabajo HRcódigo | E70: 0.3 | F70: 4.5 | G70: Tienen en el archivo de funciones, unas que no se usan, se debieron borrar. Hay g´raficas interesantes que pudieron usar en el informe, con el espacio que se aprovechaba de eliminar algunas descripciones.
A71: Trabajo HR | B71: =B65+1 -> 4 | C71: Análisis | D71: =B71&A71&C71 -> 4Trabajo HRAnálisis | E71: 0.35 | F71: 4.7 | G71: No pegar códigos, el informe es para análisis, está muy descriptivo de lo que se hizo y eso le reduce espacio a análisis, que sí tienen, pero reducido en algunas secciones como preprocesamiento o análisis exploratorio, buen análisis de metricas del modelo y propuestas
A72: Trabajo HR | B72: =B66+1 -> 4 | C72: Redacción | D72: =B72&A72&C72 -> 4Trabajo HRRedacción | E72: 0.2 | F72: 4.7 | G72: No pegar códigos, el informe es para análisis, está muy descriptivo de lo que se hizo y eso le reduce espacio a análisis, que sí tienen, pero reducido en algunas secciones como preprocesamiento o análisis exploratorio, buen análisis de metricas del modelo y propuestas
A73: Trabajo HR | B73: =B67+1 -> 4 | C73: Total | D73: =B73&A73&C73 -> 4Trabajo HRTotal | E73: =SUM(E68:E72) -> 1 | F73: =SUMPRODUCT(E68:E72,F68:F72) -> 4.605
A74: Trabajo HR | B74: =B68+1 -> 5 | C74: Creatividad | D74: =B74&A74&C74 -> 5Trabajo HRCreatividad | E74: 0.1 | F74: 5
A75: Trabajo HR | B75: =B69+1 -> 5 | C75: Pertinencia | D75: =B75&A75&C75 -> 5Trabajo HRPertinencia | E75: 0.05 | F75: 5
A76: Trabajo HR | B76: =B70+1 -> 5 | C76: código | D76: =B76&A76&C76 -> 5Trabajo HRcódigo | E76: 0.3 | F76: 5
A77: Trabajo HR | B77: =B71+1 -> 5 | C77: Análisis | D77: =B77&A77&C77 -> 5Trabajo HRAnálisis | E77: 0.35 | F77: 5
A78: Trabajo HR | B78: =B72+1 -> 5 | C78: Redacción | D78: =B78&A78&C78 -> 5Trabajo HRRedacción | E78: 0.2 | F78: 5
A79: Trabajo HR | B79: =B73+1 -> 5 | C79: Total | D79: =B79&A79&C79 -> 5Trabajo HRTotal | E79: =SUM(E74:E78) -> 1 | F79: =SUMPRODUCT(E74:E78,F74:F78) -> 5
A80: Trabajo HR | B80: =B74+1 -> 6 | C80: Creatividad | D80: =B80&A80&C80 -> 6Trabajo HRCreatividad | E80: 0.1 | F80: 4.5 | G80: Muy buena la división pro grupos de criticidad, sin embargo, las estrategias en el diseño desconocen los resultados que se van a tener posteriormente, es muy difícil proponer una estrategia desde el diseño si todavía no hay datos que lo proponga, mejor planterarla completamente después de análisis.
A81: Trabajo HR | B81: =B75+1 -> 6 | C81: Pertinencia | D81: =B81&A81&C81 -> 6Trabajo HRPertinencia | E81: 0.05 | F81: 4.5 | G81: Falto explorar los grupos propuestas con las predicciones en los datos de entrenamiento
A82: Trabajo HR | B82: =B76+1 -> 6 | C82: código | D82: =B82&A82&C82 -> 6Trabajo HRcódigo | E82: 0.3 | F82: 4.5 | G82: Faltó organizar un poco las carpetas, por ejemplo solo se necesitaba una base de datos, no dos, y estas podían ir en la carpeta de data para que no se revolvieran con los códigos
A83: Trabajo HR | B83: =B77+1 -> 6 | C83: Análisis | D83: =B83&A83&C83 -> 6Trabajo HRAnálisis | E83: 0.35 | F83: 4.3 | G83: Decir que 2016 se utiliza para validación es incorrecto, por que para usar datos como validación se necesitarían los retiros de 2017 que no se tienen, 2016 se utiliza para hacer predicción no validación.
A84: Trabajo HR | B84: =B78+1 -> 6 | C84: Redacción | D84: =B84&A84&C84 -> 6Trabajo HRRedacción | E84: 0.2 | F84: 4 | G84: No se uso bien el espacio, uan introducción muy largo, poner la lista de las tablas no era necesario y hay mucho texto explicando demasiado lo que se hace, esto se puede hacer pero en espacio más reducido para dedicar el resto al análisis, las matrices de confusión si se analizaron bien comparando los modelos, este tipo de análisis es el que debe buscar más espacio
A85: Trabajo HR | B85: =B79+1 -> 6 | C85: Total | D85: =B85&A85&C85 -> 6Trabajo HRTotal | E85: =SUM(E80:E84) -> 1 | F85: =SUMPRODUCT(E80:E84,F80:F84) -> 4.33
A86: Trabajo HR | B86: =B80+1 -> 7 | C86: Creatividad | D86: =B86&A86&C86 -> 7Trabajo HRCreatividad | E86: 0.1 | F86: 4 | G86: Buena la idea y el diseño pero no lo reflejaron en el resto del trabajo
A87: Trabajo HR | B87: =B81+1 -> 7 | C87: Pertinencia | D87: =B87&A87&C87 -> 7Trabajo HRPertinencia | E87: 0.05 | F87: 5
A88: Trabajo HR | B88: =B82+1 -> 7 | C88: código | D88: =B88&A88&C88 -> 7Trabajo HRcódigo | E88: 0.3 | F88: 3.5 | G88: El proyecto no está bien organizado, todos los archivos están en la raiz y es muy dificil dfiferenciar los códigos de salidas y datos, crean una carpeta de salidas pero muchas salidas quedaron en la raiz, hay muchas bases de datos y no es práctivo uno debería tener una y dentro todas las tablas. Los archivos no se ven enumerados. En el archivo de despliegue tienen muchos errores
A89: Trabajo HR | B89: =B83+1 -> 7 | C89: Análisis | D89: =B89&A89&C89 -> 7Trabajo HRAnálisis | E89: 0.35 | F89: 4 | G89: no se habló del despliegue ni se analizó los grupos de criticidad que se mencionaron en el diseño. Las estyrategias finales se ven muy genéricas y no basadas en los hallazgos
A90: Trabajo HR | B90: =B84+1 -> 7 | C90: Redacción | D90: =B90&A90&C90 -> 7Trabajo HRRedacción | E90: 0.2 | F90: 4 | G90: Faltó mucho análisis, les sobro espacio. El exploratorio fue muy amplio y no lo tradujeron en conclusiones, mostraron gráficos que no agregaban mucho valor
A91: Trabajo HR | B91: =B85+1 -> 7 | C91: Total | D91: =B91&A91&C91 -> 7Trabajo HRTotal | E91: =SUM(E86:E90) -> 1 | F91: =SUMPRODUCT(E86:E90,F86:F90) -> 3.9
A92: Trabajo HR | B92: =B86+1 -> 8 | C92: Creatividad | D92: =B92&A92&C92 -> 8Trabajo HRCreatividad | E92: 0.1 | F92: 4.5 | G92: El diseño está bien pero tiene muchos pasos de la construcción de modelo se puede poner un solo paso de entrenamiento y el resto del proceso de negocio que es lo importante. Faltó proponer ideas innovadores para resolver el problema
A93: Trabajo HR | B93: =B87+1 -> 8 | C93: Pertinencia | D93: =B93&A93&C93 -> 8Trabajo HRPertinencia | E93: 0.05 | F93: 4.5 | G93: Muy bien proponer una meta, y tiene buen enfoque el trabajo pero elaborar más las estrategias
A94: Trabajo HR | B94: =B88+1 -> 8 | C94: código | D94: =B94&A94&C94 -> 8Trabajo HRcódigo | E94: 0.3 | F94: 3 | G94: El código no está bien organizado, unos archivos están enumeradoscon letras y otros no, no hay carpetas para separar datos o salidas. La forma de crear las tablas no es la más eficiente, se pueden llevar directamente de pandas a sql y así se crean sin definir cada campo, tienen un archivo de funciones que no se carga en ningun otro, de hecho está en un notebook que no deja cargar, este archivo no sirve para nnada, si las funciones se van a poner dentro del código mejor borrarlo. El archivo de limpieza y exploración no se deja visualizar, pusieron análisis en el código que debería estar en el informe. Tienen errores en el archivo de modelo imprimiendo un gráfico. Tienen paquetes instalados por todo el código y falta mucho orden, tienen funciones que no usan como medir_modelos
A95: Trabajo HR | B95: =B89+1 -> 8 | C95: Análisis | D95: =B95&A95&C95 -> 8Trabajo HRAnálisis | E95: 0.35 | F95: 4 | G95: Muy buenas conclusiones de análisis exploratorio. Los resultados descritos de la matriz de confusión no con la gráfica, la gráfica aparecen en 0 unos valores que no se reportan, no se mencionó si la matriz es de evaluación o entrenamiento y no se calcualron indicadores como accuracy F1 score entre otros, en los resultados del modelo no se dijo cuál es el indicador que dio 1 y esto es Sospechoso, deberían revisar qué pudo pasar. Buen repoerte de variables importantes pero los valores no son interpretables, mejor poner el orden o volverlo porcentaje. No se reportó nada de despliegue ni de predicciónes 2017 que era el objetivo principal
A96: Trabajo HR | B96: =B90+1 -> 8 | C96: Redacción | D96: =B96&A96&C96 -> 8Trabajo HRRedacción | E96: 0.2 | F96: 4 | G96: Se gastaron una página escribiendo la información que había en la guía en lugar de aprovechar para hacer análisis y conclusiones de esa información. El documento le falta mejor organización y presentación como la tabla del diseño de la solución. No era necesario escribir las tablas ni describirlas esto no agrega valor
A97: Trabajo HR | B97: =B91+1 -> 8 | C97: Total | D97: =B97&A97&C97 -> 8Trabajo HRTotal | E97: =SUM(E92:E96) -> 1 | F97: =SUMPRODUCT(E92:E96,F92:F96) -> 3.775
A98: 4. Presentación de avances mark | B98: 1 | C98: Claridad | D98: =B98&A98&C98 -> 14. Presentación de avances markClaridad | E98: 0.2 | F98: 5
A99: 4. Presentación de avances mark | B99: 1 | C99: Avance | D99: =B99&A99&C99 -> 14. Presentación de avances markAvance | E99: 0.2 | F99: 5
A100: 4. Presentación de avances mark | B100: 1 | C100: Comprensión | D100: =B100&A100&C100 -> 14. Presentación de avances markComprensión | E100: 0.2 | F100: 5
...

Sheet seguimientos_extra
A1: Correo | B1: Nota presentación
A2: osiris.contreras@udea.edu.co | B2: 4.5 | C2: Sí
A3: jfelipe.osorio@udea.edu.co | B3: 5 | C3: Sí
A4: alejandro.alvarezl@udea.edu.co | B4: 4.7 | C4: Sí
A5: juan.arroyave14@udea.edu.co | B5: 4.8 | C5: Sí
A6: estefania.dussan@udea.edu.co | B6: 5 | C6: Sí
A7: sebastian.sanchez9@udea.edu.co | B7: 4.8 | C7: Sí
A8: paola.arabia@udea.edu.co | B8: 4.5 | C8: Sí
A9: leidys.guerrero@udea.edu.co | B9: 4.4 | C9: Sí
